[
  {
    "paragraph": [
      {
        "text": "Welcome to the 35<sup>th</sup> annual Sunbelt Cohutta "
      },
      {
        "text": "Springs Triathlon!"
      }
    ]
  },
  {
    "paragraph": [
      {
        "text": "We invite you to join us at the Cohutta Springs Conference "
      },
      {
        "text": "Center, in Crandall, GA on Sunday, October 7, 2018 - the"
      },
      {
        "text": "first Sunday of the month. Packet pickup is from 10:30 am "
      },
      {
        "text": "to 11:45 am, with orientation at 11:45 am; the race starts "
      },
      {
        "text": "at 12:30 pm. The race features a ½ mile swim, 18 mile bike, "
      },
      {
        "text": "and 4 mile run."
      }
    ]
  },
  {
    "paragraph": [
      {
        "text": "Timing and Registration is avalible at "
      },
      {
        "protocol": "https",
        "link": "sunbeltcohuttaspringstriathlon.itsyourrace.com/register/"
      },
      {
        "text": " and is handled by Scenic City Multisport. Visit our FaceBook at "
      },
      {
        "protocol": "https",
        "link": "www.facebook.com/southerntriathlon"
      },
      {
        "text": " to explore photos from the past or like and help promote this event."
      }
    ]
  }
]
