[
    {
        "category": "I",
        "sortOrder": 3,
        "ageGroup": "Female 14 - 16",
        "bibNumber": 384,
        "name": "Lilyann Adams",
        "gender": "F",
        "age": 14,
        "swimRank": 1,
        "swimTime": "1970-01-01T00:18:19.3000000",
        "T1": "1970-01-01T00:03:18.6260000",
        "bikeRank": 1,
        "bikeTime": "1970-01-01T01:13:51.2740000",
        "T2": "1970-01-01T00:00:48.4260000",
        "runRank": 1,
        "runTime": "1970-01-01T00:49:43.6870000",
        "ageGroupRank": 1,
        "overallRank": 42,
        "total": "1970-01-01T02:26:01.3130000"
    },
    {
        "category": "I",
        "sortOrder": 3,
        "ageGroup": "Female 17 - 19",
        "bibNumber": 411,
        "name": "Sydnie Ohm",
        "gender": "F",
        "age": 19,
        "swimRank": 1,
        "swimTime": "1970-01-01T00:12:17.3630000",
        "T1": "1970-01-01T00:01:35.9570000",
        "bikeRank": 2,
        "bikeTime": "1970-01-01T00:59:05.0300000",
        "T2": "1970-01-01T00:01:10.4060000",
        "runRank": 2,
        "runTime": "1970-01-01T00:34:01.7100000",
        "ageGroupRank": 1,
        "overallRank": 4,
        "total": "1970-01-01T01:48:10.4660000"
    },
    {
        "category": "I",
        "sortOrder": 3,
        "ageGroup": "Female 17 - 19",
        "bibNumber": 387,
        "name": "Jade Deschamps",
        "gender": "F",
        "age": 19,
        "swimRank": 4,
        "swimTime": "1970-01-01T00:19:13.9300000",
        "T1": "1970-01-01T00:01:08.3900000",
        "bikeRank": 1,
        "bikeTime": "1970-01-01T00:55:40.1460000",
        "T2": "1970-01-01T00:07:38.8870000",
        "runRank": 1,
        "runTime": "1970-01-01T00:31:35.7400000",
        "ageGroupRank": 2,
        "overallRank": 8,
        "total": "1970-01-01T01:55:17.0930000"
    },
    {
        "category": "I",
        "sortOrder": 3,
        "ageGroup": "Female 17 - 19",
        "bibNumber": 389,
        "name": "Hannah Wilson",
        "gender": "F",
        "age": 19,
        "swimRank": 2,
        "swimTime": "1970-01-01T00:16:20.2330000",
        "T1": "1970-01-01T00:02:03.5800000",
        "bikeRank": 3,
        "bikeTime": "1970-01-01T01:08:18.4930000",
        "T2": "1970-01-01T00:00:47.4200000",
        "runRank": 3,
        "runTime": "1970-01-01T00:39:42.8540000",
        "ageGroupRank": 3,
        "overallRank": 20,
        "total": "1970-01-01T02:07:12.5800000"
    },
    {
        "category": "I",
        "sortOrder": 3,
        "ageGroup": "Female 17 - 19",
        "bibNumber": 386,
        "name": "Sophia Nappi",
        "gender": "F",
        "age": 17,
        "swimRank": 3,
        "swimTime": "1970-01-01T00:17:13.6300000",
        "T1": "1970-01-01T00:03:07.5700000",
        "bikeRank": 5,
        "bikeTime": "1970-01-01T01:19:09.0830000",
        "T2": "1970-01-01T00:02:26.5970000",
        "runRank": 5,
        "runTime": "1970-01-01T00:52:18.6560000",
        "ageGroupRank": 4,
        "overallRank": 46,
        "total": "1970-01-01T02:34:15.5360000"
    },
    {
        "category": "I",
        "sortOrder": 3,
        "ageGroup": "Female 17 - 19",
        "bibNumber": 388,
        "name": "Megan Schlinsog",
        "gender": "F",
        "age": 19,
        "swimRank": 5,
        "swimTime": "1970-01-01T00:26:00.9500000",
        "T1": "1970-01-01T00:03:53.7300000",
        "bikeRank": 4,
        "bikeTime": "1970-01-01T01:16:12.7700000",
        "T2": "1970-01-01T00:01:48.8830000",
        "runRank": 4,
        "runTime": "1970-01-01T00:48:30.3470000",
        "ageGroupRank": 5,
        "overallRank": 49,
        "total": "1970-01-01T02:36:26.6800000"
    },
    {
        "category": "I",
        "sortOrder": 3,
        "ageGroup": "Female 20 - 24",
        "bibNumber": 312,
        "name": "Jessica Mckee",
        "gender": "F",
        "age": 20,
        "swimRank": 2,
        "swimTime": "1970-01-01T00:15:22.0800000",
        "T1": "1970-01-01T00:02:23.0000000",
        "bikeRank": 2,
        "bikeTime": "1970-01-01T00:58:15.7860000",
        "T2": "1970-01-01T00:01:25.5570000",
        "runRank": 5,
        "runTime": "1970-01-01T00:39:01.7600000",
        "ageGroupRank": 1,
        "overallRank": 9,
        "total": "1970-01-01T01:56:28.1830000"
    },
    {
        "category": "I",
        "sortOrder": 3,
        "ageGroup": "Female 20 - 24",
        "bibNumber": 345,
        "name": "Rachel Wilson",
        "gender": "F",
        "age": 23,
        "swimRank": 1,
        "swimTime": "1970-01-01T00:14:57.7000000",
        "T1": "1970-01-01T00:02:22.9230000",
        "bikeRank": 3,
        "bikeTime": "1970-01-01T01:04:44.3870000",
        "T2": "1970-01-01T00:01:33.5930000",
        "runRank": 6,
        "runTime": "1970-01-01T00:39:55.6430000",
        "ageGroupRank": 2,
        "overallRank": 13,
        "total": "1970-01-01T02:03:34.2460000"
    },
    {
        "category": "I",
        "sortOrder": 3,
        "ageGroup": "Female 20 - 24",
        "bibNumber": 344,
        "name": "Annika Lorenz",
        "gender": "F",
        "age": 23,
        "swimRank": 6,
        "swimTime": "1970-01-01T00:18:27.5960000",
        "T1": "1970-01-01T00:03:03.2870000",
        "bikeRank": 5,
        "bikeTime": "1970-01-01T01:07:22.9800000",
        "T2": "1970-01-01T00:01:38.8570000",
        "runRank": 1,
        "runTime": "1970-01-01T00:36:34.5560000",
        "ageGroupRank": 3,
        "overallRank": 19,
        "total": "1970-01-01T02:07:07.2760000"
    },
    {
        "category": "I",
        "sortOrder": 3,
        "ageGroup": "Female 20 - 24",
        "bibNumber": 313,
        "name": "April Minter",
        "gender": "F",
        "age": 20,
        "swimRank": 4,
        "swimTime": "1970-01-01T00:17:20.9900000",
        "T1": "1970-01-01T00:02:08.7460000",
        "bikeRank": 4,
        "bikeTime": "1970-01-01T01:07:21.0300000",
        "T2": "1970-01-01T00:00:50.7540000",
        "runRank": 10,
        "runTime": "1970-01-01T00:43:56.9160000",
        "ageGroupRank": 4,
        "overallRank": 26,
        "total": "1970-01-01T02:11:38.4360000"
    },
    {
        "category": "I",
        "sortOrder": 3,
        "ageGroup": "Female 20 - 24",
        "bibNumber": 358,
        "name": "Lauren Waegele",
        "gender": "F",
        "age": 20,
        "swimRank": 3,
        "swimTime": "1970-01-01T00:17:18.6600000",
        "T1": "1970-01-01T00:02:19.0130000",
        "bikeRank": 8,
        "bikeTime": "1970-01-01T01:09:16.5530000",
        "T2": "1970-01-01T00:01:24.5640000",
        "runRank": 12,
        "runTime": "1970-01-01T00:45:02.8800000",
        "ageGroupRank": 5,
        "overallRank": 29,
        "total": "1970-01-01T02:15:21.6700000"
    },
    {
        "category": "I",
        "sortOrder": 3,
        "ageGroup": "Female 20 - 24",
        "bibNumber": 339,
        "name": "Katelyn Juneau",
        "gender": "F",
        "age": 21,
        "swimRank": 5,
        "swimTime": "1970-01-01T00:17:50.4830000",
        "T1": "1970-01-01T00:02:46.1030000",
        "bikeRank": 10,
        "bikeTime": "1970-01-01T01:15:57.6870000",
        "T2": "1970-01-01T00:01:07.7000000",
        "runRank": 4,
        "runTime": "1970-01-01T00:39:00.1770000",
        "ageGroupRank": 6,
        "overallRank": 31,
        "total": "1970-01-01T02:16:42.1500000"
    },
    {
        "category": "I",
        "sortOrder": 3,
        "ageGroup": "Female 20 - 24",
        "bibNumber": 311,
        "name": "Alexandria Martin",
        "gender": "F",
        "age": 20,
        "swimRank": 10,
        "swimTime": "1970-01-01T00:22:03.6100000",
        "T1": "1970-01-01T00:02:42.6130000",
        "bikeRank": 7,
        "bikeTime": "1970-01-01T01:08:44.9430000",
        "T2": "1970-01-01T00:01:38.2900000",
        "runRank": 11,
        "runTime": "1970-01-01T00:44:44.9340000",
        "ageGroupRank": 7,
        "overallRank": 36,
        "total": "1970-01-01T02:19:54.3900000"
    },
    {
        "category": "I",
        "sortOrder": 3,
        "ageGroup": "Female 20 - 24",
        "bibNumber": 343,
        "name": "Rachel Halterman",
        "gender": "F",
        "age": 22,
        "swimRank": 12,
        "swimTime": "1970-01-01T00:25:38.7900000",
        "T1": "1970-01-01T00:02:34.2360000",
        "bikeRank": 6,
        "bikeTime": "1970-01-01T01:08:10.8140000",
        "T2": "1970-01-01T00:01:49.2930000",
        "runRank": 7,
        "runTime": "1970-01-01T00:41:53.8330000",
        "ageGroupRank": 8,
        "overallRank": 37,
        "total": "1970-01-01T02:20:06.9660000"
    },
    {
        "category": "I",
        "sortOrder": 3,
        "ageGroup": "Female 20 - 24",
        "bibNumber": 310,
        "name": "Kristine Koliadko",
        "gender": "F",
        "age": 20,
        "swimRank": 7,
        "swimTime": "1970-01-01T00:20:16.9060000",
        "T1": "1970-01-01T00:03:39.9540000",
        "bikeRank": 9,
        "bikeTime": "1970-01-01T01:13:10.6300000",
        "T2": "1970-01-01T00:01:10.6800000",
        "runRank": 9,
        "runTime": "1970-01-01T00:43:11.2830000",
        "ageGroupRank": 9,
        "overallRank": 39,
        "total": "1970-01-01T02:21:29.4530000"
    },
    {
        "category": "I",
        "sortOrder": 3,
        "ageGroup": "Female 20 - 24",
        "bibNumber": 338,
        "name": "Julia Bassell",
        "gender": "F",
        "age": 21,
        "swimRank": 9,
        "swimTime": "1970-01-01T00:21:23.4200000",
        "T1": "1970-01-01T01:23:58.3600000",
        "bikeRank": 1,
        "bikeTime": "1970-01-01T00:00:00.0000000",
        "T2": "1970-01-01T00:01:27.4130000",
        "runRank": 3,
        "runTime": "1970-01-01T00:38:04.1800000",
        "ageGroupRank": 10,
        "overallRank": 40,
        "total": "1970-01-01T02:24:53.3730000"
    },
    {
        "category": "I",
        "sortOrder": 3,
        "ageGroup": "Female 20 - 24",
        "bibNumber": 341,
        "name": "Mindy Ross",
        "gender": "F",
        "age": 21,
        "swimRank": 8,
        "swimTime": "1970-01-01T00:20:59.2600000",
        "T1": "1970-01-01T00:06:26.8600000",
        "bikeRank": 11,
        "bikeTime": "1970-01-01T01:17:58.5960000",
        "T2": "1970-01-01T00:01:25.3070000",
        "runRank": 2,
        "runTime": "1970-01-01T00:38:03.3670000",
        "ageGroupRank": 11,
        "overallRank": 41,
        "total": "1970-01-01T02:24:53.3900000"
    },
    {
        "category": "I",
        "sortOrder": 3,
        "ageGroup": "Female 20 - 24",
        "bibNumber": 314,
        "name": "Rachelle Pichot",
        "gender": "F",
        "age": 20,
        "swimRank": 11,
        "swimTime": "1970-01-01T00:23:12.5430000",
        "T1": "1970-01-01T00:05:07.0970000",
        "bikeRank": 12,
        "bikeTime": "1970-01-01T01:23:09.2100000",
        "T2": "1970-01-01T00:01:03.9130000",
        "runRank": 8,
        "runTime": "1970-01-01T00:42:32.0730000",
        "ageGroupRank": 12,
        "overallRank": 48,
        "total": "1970-01-01T02:35:04.8360000"
    },
    {
        "category": "I",
        "sortOrder": 3,
        "ageGroup": "Female 25 - 29",
        "bibNumber": 357,
        "name": "Hanniel Krohne",
        "gender": "F",
        "age": 28,
        "swimRank": 1,
        "swimTime": "1970-01-01T00:14:43.6100000",
        "T1": "1970-01-01T00:03:55.5270000",
        "bikeRank": 1,
        "bikeTime": "1970-01-01T00:57:28.0530000",
        "T2": "1970-01-01T00:02:59.9430000",
        "runRank": 2,
        "runTime": "1970-01-01T00:34:31.4640000",
        "ageGroupRank": 1,
        "overallRank": 7,
        "total": "1970-01-01T01:53:38.5970000"
    },
    {
        "category": "I",
        "sortOrder": 3,
        "ageGroup": "Female 25 - 29",
        "bibNumber": 350,
        "name": "Traci Sherbondy",
        "gender": "F",
        "age": 29,
        "swimRank": 2,
        "swimTime": "1970-01-01T00:16:48.9300000",
        "T1": "1970-01-01T00:01:56.2600000",
        "bikeRank": 2,
        "bikeTime": "1970-01-01T00:58:17.8860000",
        "T2": "1970-01-01T00:01:21.2770000",
        "runRank": 3,
        "runTime": "1970-01-01T00:40:00.9630000",
        "ageGroupRank": 2,
        "overallRank": 10,
        "total": "1970-01-01T01:58:25.3160000"
    },
    {
        "category": "I",
        "sortOrder": 3,
        "ageGroup": "Female 25 - 29",
        "bibNumber": 351,
        "name": "Taylor Womack",
        "gender": "F",
        "age": 29,
        "swimRank": 3,
        "swimTime": "1970-01-01T00:16:55.1600000",
        "T1": "1970-01-01T00:02:50.1660000",
        "bikeRank": 4,
        "bikeTime": "1970-01-01T01:04:01.9140000",
        "T2": "1970-01-01T00:02:27.5900000",
        "runRank": 1,
        "runTime": "1970-01-01T00:34:01.9460000",
        "ageGroupRank": 3,
        "overallRank": 11,
        "total": "1970-01-01T02:00:16.7760000"
    },
    {
        "category": "I",
        "sortOrder": 3,
        "ageGroup": "Female 25 - 29",
        "bibNumber": 348,
        "name": "Laura Foster",
        "gender": "F",
        "age": 29,
        "swimRank": 4,
        "swimTime": "1970-01-01T00:18:59.9600000",
        "T1": "1970-01-01T00:02:36.9360000",
        "bikeRank": 3,
        "bikeTime": "1970-01-01T01:03:52.6540000",
        "T2": "1970-01-01T00:01:36.2230000",
        "runRank": 5,
        "runTime": "1970-01-01T00:43:00.6870000",
        "ageGroupRank": 4,
        "overallRank": 22,
        "total": "1970-01-01T02:10:06.4600000"
    },
    {
        "category": "I",
        "sortOrder": 3,
        "ageGroup": "Female 25 - 29",
        "bibNumber": 347,
        "name": "Amy Ward",
        "gender": "F",
        "age": 26,
        "swimRank": 5,
        "swimTime": "1970-01-01T00:19:58.3100000",
        "T1": "1970-01-01T00:03:17.7900000",
        "bikeRank": 5,
        "bikeTime": "1970-01-01T01:15:11.1900000",
        "T2": "1970-01-01T00:01:30.5430000",
        "runRank": 6,
        "runTime": "1970-01-01T00:52:16.4530000",
        "ageGroupRank": 5,
        "overallRank": 45,
        "total": "1970-01-01T02:32:14.2860000"
    },
    {
        "category": "I",
        "sortOrder": 3,
        "ageGroup": "Female 25 - 29",
        "bibNumber": 349,
        "name": "Laudeli Hugel",
        "gender": "F",
        "age": 29,
        "swimRank": 6,
        "swimTime": "1970-01-01T00:24:44.1700000",
        "T1": "1970-01-01T00:04:57.4060000",
        "bikeRank": 6,
        "bikeTime": "1970-01-01T01:20:57.2670000",
        "T2": "1970-01-01T00:01:32.1830000",
        "runRank": 4,
        "runTime": "1970-01-01T00:42:13.0640000",
        "ageGroupRank": 6,
        "overallRank": 47,
        "total": "1970-01-01T02:34:24.0900000"
    },
    {
        "category": "I",
        "sortOrder": 3,
        "ageGroup": "Female 30 - 34",
        "bibNumber": 355,
        "name": "Megan Moore",
        "gender": "F",
        "age": 33,
        "swimRank": 1,
        "swimTime": "1970-01-01T00:18:42.2100000",
        "T1": "1970-01-01T00:01:54.1460000",
        "bikeRank": 1,
        "bikeTime": "1970-01-01T01:05:26.1200000",
        "T2": "1970-01-01T00:01:27.2940000",
        "runRank": 1,
        "runTime": "1970-01-01T00:34:26.4430000",
        "ageGroupRank": 1,
        "overallRank": 12,
        "total": "1970-01-01T02:01:56.2130000"
    },
    {
        "category": "I",
        "sortOrder": 3,
        "ageGroup": "Female 30 - 34",
        "bibNumber": 356,
        "name": "Janelle Shives",
        "gender": "F",
        "age": 34,
        "swimRank": 2,
        "swimTime": "1970-01-01T00:18:42.3060000",
        "T1": "1970-01-01T00:02:33.5240000",
        "bikeRank": 2,
        "bikeTime": "1970-01-01T01:07:41.3030000",
        "T2": "1970-01-01T00:02:21.8200000",
        "runRank": 2,
        "runTime": "1970-01-01T00:45:40.6630000",
        "ageGroupRank": 2,
        "overallRank": 32,
        "total": "1970-01-01T02:16:59.6160000"
    },
    {
        "category": "I",
        "sortOrder": 3,
        "ageGroup": "Female 30 - 34",
        "bibNumber": 353,
        "name": "Samantha Griffin",
        "gender": "F",
        "age": 30,
        "swimRank": 3,
        "swimTime": "1970-01-01T00:22:51.2260000",
        "T1": "1970-01-01T00:05:11.0140000",
        "bikeRank": 3,
        "bikeTime": "1970-01-01T01:13:06.7100000",
        "T2": "1970-01-01T00:02:36.8400000",
        "runRank": 3,
        "runTime": "1970-01-01T00:48:28.4330000",
        "ageGroupRank": 3,
        "overallRank": 44,
        "total": "1970-01-01T02:32:14.2230000"
    },
    {
        "category": "I",
        "sortOrder": 3,
        "ageGroup": "Female 35 - 39",
        "bibNumber": 360,
        "name": "Leslie Evenson",
        "gender": "F",
        "age": 35,
        "swimRank": 2,
        "swimTime": "1970-01-01T00:17:31.1000000",
        "T1": "1970-01-01T00:02:06.1130000",
        "bikeRank": 1,
        "bikeTime": "1970-01-01T00:55:54.2770000",
        "T2": "1970-01-01T00:01:04.9300000",
        "runRank": 1,
        "runTime": "1970-01-01T00:32:39.0330000",
        "ageGroupRank": 1,
        "overallRank": 5,
        "total": "1970-01-01T01:49:15.4530000"
    },
    {
        "category": "I",
        "sortOrder": 3,
        "ageGroup": "Female 35 - 39",
        "bibNumber": 380,
        "name": "Rebecca Keach",
        "gender": "F",
        "age": 36,
        "swimRank": 1,
        "swimTime": "1970-01-01T00:17:10.7330000",
        "T1": "1970-01-01T00:02:19.1470000",
        "bikeRank": 3,
        "bikeTime": "1970-01-01T01:04:15.0130000",
        "T2": "1970-01-01T00:01:06.9840000",
        "runRank": 2,
        "runTime": "1970-01-01T00:39:08.1800000",
        "ageGroupRank": 2,
        "overallRank": 14,
        "total": "1970-01-01T02:04:00.0570000"
    },
    {
        "category": "I",
        "sortOrder": 3,
        "ageGroup": "Female 35 - 39",
        "bibNumber": 363,
        "name": "Kalie Kelch",
        "gender": "F",
        "age": 38,
        "swimRank": 3,
        "swimTime": "1970-01-01T00:18:25.1070000",
        "T1": "1970-01-01T00:03:27.1460000",
        "bikeRank": 2,
        "bikeTime": "1970-01-01T01:01:30.5040000",
        "T2": "1970-01-01T00:01:36.4660000",
        "runRank": 4,
        "runTime": "1970-01-01T00:41:10.0170000",
        "ageGroupRank": 3,
        "overallRank": 16,
        "total": "1970-01-01T02:06:09.2400000"
    },
    {
        "category": "I",
        "sortOrder": 3,
        "ageGroup": "Female 35 - 39",
        "bibNumber": 361,
        "name": "Sarah Blount",
        "gender": "F",
        "age": 36,
        "swimRank": 4,
        "swimTime": "1970-01-01T00:20:34.4630000",
        "T1": "1970-01-01T00:02:32.2070000",
        "bikeRank": 4,
        "bikeTime": "1970-01-01T01:08:18.7000000",
        "T2": "1970-01-01T00:01:02.8370000",
        "runRank": 3,
        "runTime": "1970-01-01T00:41:08.6800000",
        "ageGroupRank": 4,
        "overallRank": 27,
        "total": "1970-01-01T02:13:36.8870000"
    },
    {
        "category": "I",
        "sortOrder": 3,
        "ageGroup": "Female 40 - 44",
        "bibNumber": 368,
        "name": "Rebecca Stein",
        "gender": "F",
        "age": 43,
        "swimRank": 1,
        "swimTime": "1970-01-01T00:17:15.5770000",
        "T1": "1970-01-01T00:02:59.5300000",
        "bikeRank": 4,
        "bikeTime": "1970-01-01T01:02:53.3730000",
        "T2": "1970-01-01T00:02:22.4270000",
        "runRank": 3,
        "runTime": "1970-01-01T00:41:10.5830000",
        "ageGroupRank": 1,
        "overallRank": 17,
        "total": "1970-01-01T02:06:41.4900000"
    },
    {
        "category": "I",
        "sortOrder": 3,
        "ageGroup": "Female 40 - 44",
        "bibNumber": 381,
        "name": "Tamatha Farrow",
        "gender": "F",
        "age": 44,
        "swimRank": 2,
        "swimTime": "1970-01-01T00:18:28.5830000",
        "T1": "1970-01-01T00:02:14.9500000",
        "bikeRank": 2,
        "bikeTime": "1970-01-01T00:58:00.5170000",
        "T2": "1970-01-01T00:02:34.5330000",
        "runRank": 4,
        "runTime": "1970-01-01T00:46:10.6400000",
        "ageGroupRank": 2,
        "overallRank": 21,
        "total": "1970-01-01T02:07:29.2230000"
    },
    {
        "category": "I",
        "sortOrder": 3,
        "ageGroup": "Female 40 - 44",
        "bibNumber": 366,
        "name": "Renea Fox",
        "gender": "F",
        "age": 40,
        "swimRank": 4,
        "swimTime": "1970-01-01T00:21:57.1770000",
        "T1": "1970-01-01T00:03:19.9060000",
        "bikeRank": 3,
        "bikeTime": "1970-01-01T01:02:43.7740000",
        "T2": "1970-01-01T00:02:32.5660000",
        "runRank": 2,
        "runTime": "1970-01-01T00:40:32.8870000",
        "ageGroupRank": 3,
        "overallRank": 24,
        "total": "1970-01-01T02:11:06.3100000"
    },
    {
        "category": "I",
        "sortOrder": 3,
        "ageGroup": "Female 40 - 44",
        "bibNumber": 367,
        "name": "Kerri Oskouei",
        "gender": "F",
        "age": 43,
        "swimRank": 3,
        "swimTime": "1970-01-01T00:20:06.1870000",
        "T1": "1970-01-01T01:19:02.5460000",
        "bikeRank": 1,
        "bikeTime": "1970-01-01T00:00:00.0000000",
        "T2": "1970-01-01T00:01:06.6640000",
        "runRank": 1,
        "runTime": "1970-01-01T00:37:19.2860000",
        "ageGroupRank": 4,
        "overallRank": 34,
        "total": "1970-01-01T02:17:34.6830000"
    },
    {
        "category": "I",
        "sortOrder": 3,
        "ageGroup": "Female 45 - 49",
        "bibNumber": 371,
        "name": "Alisa Brogdon",
        "gender": "F",
        "age": 46,
        "swimRank": 2,
        "swimTime": "1970-01-01T00:18:14.9270000",
        "T1": "1970-01-01T00:02:28.5160000",
        "bikeRank": 1,
        "bikeTime": "1970-01-01T00:57:30.4840000",
        "T2": "1970-01-01T00:01:55.3100000",
        "runRank": 6,
        "runTime": "1970-01-01T00:44:57.0030000",
        "ageGroupRank": 1,
        "overallRank": 15,
        "total": "1970-01-01T02:05:06.2400000"
    },
    {
        "category": "I",
        "sortOrder": 3,
        "ageGroup": "Female 45 - 49",
        "bibNumber": 372,
        "name": "Mary Millians",
        "gender": "F",
        "age": 46,
        "swimRank": 1,
        "swimTime": "1970-01-01T00:15:31.9270000",
        "T1": "1970-01-01T00:03:53.4030000",
        "bikeRank": 2,
        "bikeTime": "1970-01-01T01:06:15.5170000",
        "T2": "1970-01-01T00:02:21.5730000",
        "runRank": 4,
        "runTime": "1970-01-01T00:43:34.7000000",
        "ageGroupRank": 2,
        "overallRank": 25,
        "total": "1970-01-01T02:11:37.1200000"
    },
    {
        "category": "I",
        "sortOrder": 3,
        "ageGroup": "Female 45 - 49",
        "bibNumber": 374,
        "name": "Rebekah Manley",
        "gender": "F",
        "age": 48,
        "swimRank": 3,
        "swimTime": "1970-01-01T00:18:31.9470000",
        "T1": "1970-01-01T00:02:49.7730000",
        "bikeRank": 6,
        "bikeTime": "1970-01-01T01:09:33.0500000",
        "T2": "1970-01-01T00:01:49.1070000",
        "runRank": 2,
        "runTime": "1970-01-01T00:41:20.6330000",
        "ageGroupRank": 3,
        "overallRank": 28,
        "total": "1970-01-01T02:14:04.5100000"
    },
    {
        "category": "I",
        "sortOrder": 3,
        "ageGroup": "Female 45 - 49",
        "bibNumber": 369,
        "name": "Sonja Fordham",
        "gender": "F",
        "age": 45,
        "swimRank": 6,
        "swimTime": "1970-01-01T00:24:08.1000000",
        "T1": "1970-01-01T00:03:30.9470000",
        "bikeRank": 4,
        "bikeTime": "1970-01-01T01:09:11.6460000",
        "T2": "1970-01-01T00:02:32.0440000",
        "runRank": 1,
        "runTime": "1970-01-01T00:36:48.3330000",
        "ageGroupRank": 4,
        "overallRank": 30,
        "total": "1970-01-01T02:16:11.0700000"
    },
    {
        "category": "I",
        "sortOrder": 3,
        "ageGroup": "Female 45 - 49",
        "bibNumber": 375,
        "name": "Angela Williams",
        "gender": "F",
        "age": 49,
        "swimRank": 5,
        "swimTime": "1970-01-01T00:21:37.3270000",
        "T1": "1970-01-01T00:03:24.8330000",
        "bikeRank": 5,
        "bikeTime": "1970-01-01T01:09:20.4930000",
        "T2": "1970-01-01T00:02:38.2370000",
        "runRank": 3,
        "runTime": "1970-01-01T00:42:29.2670000",
        "ageGroupRank": 5,
        "overallRank": 35,
        "total": "1970-01-01T02:19:30.1570000"
    },
    {
        "category": "I",
        "sortOrder": 3,
        "ageGroup": "Female 45 - 49",
        "bibNumber": 373,
        "name": "Marla Hood",
        "gender": "F",
        "age": 48,
        "swimRank": 4,
        "swimTime": "1970-01-01T00:21:07.2030000",
        "T1": "1970-01-01T00:03:58.0900000",
        "bikeRank": 3,
        "bikeTime": "1970-01-01T01:08:23.8640000",
        "T2": "1970-01-01T00:02:32.2800000",
        "runRank": 5,
        "runTime": "1970-01-01T00:44:39.3700000",
        "ageGroupRank": 6,
        "overallRank": 38,
        "total": "1970-01-01T02:20:40.8070000"
    },
    {
        "category": "I",
        "sortOrder": 3,
        "ageGroup": "Female 50 - 54",
        "bibNumber": 377,
        "name": "Suzann Findley",
        "gender": "F",
        "age": 54,
        "swimRank": 1,
        "swimTime": "1970-01-01T00:15:13.6800000",
        "T1": "1970-01-01T00:02:44.0270000",
        "bikeRank": 1,
        "bikeTime": "1970-01-01T01:05:49.0130000",
        "T2": "1970-01-01T00:01:09.3600000",
        "runRank": 2,
        "runTime": "1970-01-01T00:42:02.3230000",
        "ageGroupRank": 1,
        "overallRank": 18,
        "total": "1970-01-01T02:06:58.4030000"
    },
    {
        "category": "I",
        "sortOrder": 3,
        "ageGroup": "Female 50 - 54",
        "bibNumber": 376,
        "name": "Jan Rivers",
        "gender": "F",
        "age": 51,
        "swimRank": 2,
        "swimTime": "1970-01-01T00:19:37.9270000",
        "T1": "1970-01-01T00:02:26.2700000",
        "bikeRank": 2,
        "bikeTime": "1970-01-01T01:07:37.8030000",
        "T2": "1970-01-01T00:01:57.8500000",
        "runRank": 1,
        "runTime": "1970-01-01T00:39:00.8900000",
        "ageGroupRank": 2,
        "overallRank": 23,
        "total": "1970-01-01T02:10:40.7400000"
    },
    {
        "category": "I",
        "sortOrder": 3,
        "ageGroup": "Female 55 - 59",
        "bibNumber": 379,
        "name": "Taryn Perkins",
        "gender": "F",
        "age": 59,
        "swimRank": 1,
        "swimTime": "1970-01-01T00:18:09.3700000",
        "T1": "1970-01-01T00:03:09.0100000",
        "bikeRank": 2,
        "bikeTime": "1970-01-01T01:10:49.4870000",
        "T2": "1970-01-01T00:01:03.0930000",
        "runRank": 1,
        "runTime": "1970-01-01T00:43:53.7570000",
        "ageGroupRank": 1,
        "overallRank": 33,
        "total": "1970-01-01T02:17:04.7170000"
    },
    {
        "category": "I",
        "sortOrder": 3,
        "ageGroup": "Female 55 - 59",
        "bibNumber": 378,
        "name": "Janice Wycherley",
        "gender": "F",
        "age": 57,
        "swimRank": 2,
        "swimTime": "1970-01-01T00:21:46.4770000",
        "T1": "1970-01-01T01:16:06.0030000",
        "bikeRank": 1,
        "bikeTime": "1970-01-01T00:00:00.0000000",
        "T2": "1970-01-01T00:02:20.0330000",
        "runRank": 2,
        "runTime": "1970-01-01T00:49:40.6400000",
        "ageGroupRank": 2,
        "overallRank": 43,
        "total": "1970-01-01T02:29:53.1530000"
    },
    {
        "category": "I",
        "sortOrder": 2,
        "ageGroup": "Female Master",
        "bibNumber": 370,
        "name": "Heather Tarpley",
        "gender": "F",
        "age": 45,
        "swimRank": 1,
        "swimTime": "1970-01-01T00:14:52.4370000",
        "T1": "1970-01-01T00:02:11.0060000",
        "bikeRank": 1,
        "bikeTime": "1970-01-01T00:57:26.0440000",
        "T2": "1970-01-01T00:01:08.5600000",
        "runRank": 1,
        "runTime": "1970-01-01T00:33:41.3230000",
        "ageGroupRank": 1,
        "overallRank": 6,
        "total": "1970-01-01T01:49:19.3700000"
    },
    {
        "category": "I",
        "sortOrder": 1,
        "ageGroup": "Female Overall",
        "bibNumber": 385,
        "name": "Miriam Burnette",
        "gender": "F",
        "age": 16,
        "swimRank": 1,
        "swimTime": "1970-01-01T00:13:00.2300000",
        "T1": "1970-01-01T00:01:14.7600000",
        "bikeRank": 2,
        "bikeTime": "1970-01-01T00:55:50.3300000",
        "T2": "1970-01-01T00:00:48.9600000",
        "runRank": 3,
        "runTime": "1970-01-01T00:34:30.2130000",
        "ageGroupRank": 1,
        "overallRank": 1,
        "total": "1970-01-01T01:45:24.4930000"
    },
    {
        "category": "I",
        "sortOrder": 1,
        "ageGroup": "Female Overall",
        "bibNumber": 354,
        "name": "Jenny Delong",
        "gender": "F",
        "age": 33,
        "swimRank": 2,
        "swimTime": "1970-01-01T00:15:15.6560000",
        "T1": "1970-01-01T00:02:24.1100000",
        "bikeRank": 1,
        "bikeTime": "1970-01-01T00:53:01.6000000",
        "T2": "1970-01-01T00:01:17.8570000",
        "runRank": 2,
        "runTime": "1970-01-01T00:33:37.5470000",
        "ageGroupRank": 2,
        "overallRank": 2,
        "total": "1970-01-01T01:45:36.7700000"
    },
    {
        "category": "I",
        "sortOrder": 1,
        "ageGroup": "Female Overall",
        "bibNumber": 342,
        "name": "Sharlie Brooks",
        "gender": "F",
        "age": 22,
        "swimRank": 3,
        "swimTime": "1970-01-01T00:18:11.2130000",
        "T1": "1970-01-01T00:01:40.3170000",
        "bikeRank": 3,
        "bikeTime": "1970-01-01T00:56:05.9700000",
        "T2": "1970-01-01T00:01:34.4000000",
        "runRank": 1,
        "runTime": "1970-01-01T00:29:20.3900000",
        "ageGroupRank": 3,
        "overallRank": 3,
        "total": "1970-01-01T01:46:52.2900000"
    },
    {
        "category": "R",
        "sortOrder": 3,
        "ageGroup": "Female Relay",
        "bibNumber": 296,
        "name": "4 the Fun of It",
        "gender": "F",
        "age": 30,
        "swimRank": 2,
        "swimTime": "1970-01-01T00:14:49.9030000",
        "T1": "1970-01-01T00:01:18.0240000",
        "bikeRank": 1,
        "bikeTime": "1970-01-01T00:50:58.9360000",
        "T2": "1970-01-01T00:00:47.5740000",
        "runRank": 4,
        "runTime": "1970-01-01T00:43:37.0800000",
        "ageGroupRank": 1,
        "overallRank": 1,
        "total": "1970-01-01T01:51:31.5170000"
    },
    {
        "category": "R",
        "sortOrder": 3,
        "ageGroup": "Female Relay",
        "bibNumber": 297,
        "name": "The Procrastinators",
        "gender": "F",
        "age": 21,
        "swimRank": 1,
        "swimTime": "1970-01-01T00:14:02.1600000",
        "T1": "1970-01-01T00:01:23.6100000",
        "bikeRank": 2,
        "bikeTime": "1970-01-01T01:07:29.1930000",
        "T2": "1970-01-01T00:01:06.7170000",
        "runRank": 2,
        "runTime": "1970-01-01T00:38:36.3400000",
        "ageGroupRank": 2,
        "overallRank": 2,
        "total": "1970-01-01T02:02:38.0200000"
    },
    {
        "category": "R",
        "sortOrder": 3,
        "ageGroup": "Female Relay",
        "bibNumber": 308,
        "name": "KyHay",
        "gender": "F",
        "age": 15,
        "swimRank": 4,
        "swimTime": "1970-01-01T00:20:35.5530000",
        "T1": "1970-01-01T00:01:30.1570000",
        "bikeRank": 3,
        "bikeTime": "1970-01-01T01:14:05.7800000",
        "T2": "1970-01-01T00:00:43.0570000",
        "runRank": 1,
        "runTime": "1970-01-01T00:36:07.3360000",
        "ageGroupRank": 3,
        "overallRank": 3,
        "total": "1970-01-01T02:13:01.8830000"
    },
    {
        "category": "R",
        "sortOrder": 3,
        "ageGroup": "Female Relay",
        "bibNumber": 301,
        "name": "Las Tres Amigas",
        "gender": "F",
        "age": 21,
        "swimRank": 3,
        "swimTime": "1970-01-01T00:16:33.9300000",
        "T1": "1970-01-01T00:01:34.1300000",
        "bikeRank": 4,
        "bikeTime": "1970-01-01T01:14:49.3670000",
        "T2": "1970-01-01T00:00:41.5130000",
        "runRank": 5,
        "runTime": "1970-01-01T00:45:51.5000000",
        "ageGroupRank": 4,
        "overallRank": 4,
        "total": "1970-01-01T02:19:30.4400000"
    },
    {
        "category": "R",
        "sortOrder": 3,
        "ageGroup": "Female Relay",
        "bibNumber": 306,
        "name": "Is-Jen-Mad",
        "gender": "F",
        "age": 11,
        "swimRank": 5,
        "swimTime": "1970-01-01T00:20:47.7100000",
        "T1": "1970-01-01T00:01:20.4900000",
        "bikeRank": 5,
        "bikeTime": "1970-01-01T01:32:59.1100000",
        "T2": "1970-01-01T00:00:37.4270000",
        "runRank": 3,
        "runTime": "1970-01-01T00:41:10.7430000",
        "ageGroupRank": 5,
        "overallRank": 5,
        "total": "1970-01-01T02:36:55.4800000"
    },
    {
        "category": "I",
        "sortOrder": 3,
        "ageGroup": "Male 13 and Under",
        "bibNumber": 391,
        "name": "Joseph Urbanowicz",
        "gender": "M",
        "age": 13,
        "swimRank": 1,
        "swimTime": "1970-01-01T00:15:45.8230000",
        "T1": "1970-01-01T00:02:26.0630000",
        "bikeRank": 1,
        "bikeTime": "1970-01-01T00:58:33.4400000",
        "T2": "1970-01-01T00:01:37.2140000",
        "runRank": 1,
        "runTime": "1970-01-01T00:29:02.7700000",
        "ageGroupRank": 1,
        "overallRank": 24,
        "total": "1970-01-01T01:47:25.3100000"
    },
    {
        "category": "I",
        "sortOrder": 3,
        "ageGroup": "Male 14 - 16",
        "bibNumber": 394,
        "name": "Joby Nash",
        "gender": "M",
        "age": 14,
        "swimRank": 1,
        "swimTime": "1970-01-01T00:12:16.5160000",
        "T1": "1970-01-01T00:01:24.0140000",
        "bikeRank": 3,
        "bikeTime": "1970-01-01T00:54:04.2130000",
        "T2": "1970-01-01T00:01:06.7270000",
        "runRank": 2,
        "runTime": "1970-01-01T00:30:16.1530000",
        "ageGroupRank": 1,
        "overallRank": 16,
        "total": "1970-01-01T01:39:07.6230000"
    },
    {
        "category": "I",
        "sortOrder": 3,
        "ageGroup": "Male 14 - 16",
        "bibNumber": 402,
        "name": "Ondra Zapletal",
        "gender": "M",
        "age": 16,
        "swimRank": 2,
        "swimTime": "1970-01-01T00:14:24.4360000",
        "T1": "1970-01-01T00:02:15.1740000",
        "bikeRank": 4,
        "bikeTime": "1970-01-01T00:57:40.8700000",
        "T2": "1970-01-01T00:00:55.7230000",
        "runRank": 3,
        "runTime": "1970-01-01T00:30:42.0230000",
        "ageGroupRank": 2,
        "overallRank": 21,
        "total": "1970-01-01T01:45:58.2260000"
    },
    {
        "category": "I",
        "sortOrder": 3,
        "ageGroup": "Male 14 - 16",
        "bibNumber": 396,
        "name": "Nathan Moses",
        "gender": "M",
        "age": 15,
        "swimRank": 6,
        "swimTime": "1970-01-01T00:18:28.1960000",
        "T1": "1970-01-01T00:03:39.6540000",
        "bikeRank": 2,
        "bikeTime": "1970-01-01T00:52:32.4460000",
        "T2": "1970-01-01T00:01:20.5470000",
        "runRank": 1,
        "runTime": "1970-01-01T00:30:09.7800000",
        "ageGroupRank": 3,
        "overallRank": 22,
        "total": "1970-01-01T01:46:10.6230000"
    },
    {
        "category": "I",
        "sortOrder": 3,
        "ageGroup": "Male 14 - 16",
        "bibNumber": 397,
        "name": "Wyatt Tracy",
        "gender": "M",
        "age": 15,
        "swimRank": 3,
        "swimTime": "1970-01-01T00:15:39.0560000",
        "T1": "1970-01-01T00:56:15.6240000",
        "bikeRank": 1,
        "bikeTime": "1970-01-01T00:00:00.0000000",
        "T2": "1970-01-01T00:01:36.0100000",
        "runRank": 4,
        "runTime": "1970-01-01T00:35:25.5330000",
        "ageGroupRank": 4,
        "overallRank": 25,
        "total": "1970-01-01T01:48:56.2230000"
    },
    {
        "category": "I",
        "sortOrder": 3,
        "ageGroup": "Male 14 - 16",
        "bibNumber": 400,
        "name": "Micah Kelley",
        "gender": "M",
        "age": 16,
        "swimRank": 5,
        "swimTime": "1970-01-01T00:18:21.9630000",
        "T1": "1970-01-01T00:03:33.9300000",
        "bikeRank": 5,
        "bikeTime": "1970-01-01T01:00:15.8300000",
        "T2": "1970-01-01T00:01:01.8830000",
        "runRank": 6,
        "runTime": "1970-01-01T00:38:16.2900000",
        "ageGroupRank": 5,
        "overallRank": 51,
        "total": "1970-01-01T02:01:29.8960000"
    },
    {
        "category": "I",
        "sortOrder": 3,
        "ageGroup": "Male 14 - 16",
        "bibNumber": 392,
        "name": "Matthew Elkins",
        "gender": "M",
        "age": 14,
        "swimRank": 7,
        "swimTime": "1970-01-01T00:18:40.4100000",
        "T1": "1970-01-01T00:02:23.1860000",
        "bikeRank": 6,
        "bikeTime": "1970-01-01T01:09:27.6540000",
        "T2": "1970-01-01T00:00:43.6130000",
        "runRank": 5,
        "runTime": "1970-01-01T00:36:07.5470000",
        "ageGroupRank": 6,
        "overallRank": 58,
        "total": "1970-01-01T02:07:22.4100000"
    },
    {
        "category": "I",
        "sortOrder": 3,
        "ageGroup": "Male 14 - 16",
        "bibNumber": 399,
        "name": "Miguel Gutierrez",
        "gender": "M",
        "age": 16,
        "swimRank": 9,
        "swimTime": "1970-01-01T00:24:19.6300000",
        "T1": "1970-01-01T00:03:19.2330000",
        "bikeRank": 7,
        "bikeTime": "1970-01-01T01:11:57.2830000",
        "T2": "1970-01-01T00:01:45.3870000",
        "runRank": 8,
        "runTime": "1970-01-01T00:45:33.4370000",
        "ageGroupRank": 7,
        "overallRank": 75,
        "total": "1970-01-01T02:26:54.9700000"
    },
    {
        "category": "I",
        "sortOrder": 3,
        "ageGroup": "Male 14 - 16",
        "bibNumber": 398,
        "name": "Joshua Clinton",
        "gender": "M",
        "age": 16,
        "swimRank": 4,
        "swimTime": "1970-01-01T00:17:10.3660000",
        "T1": "1970-01-01T00:03:11.8900000",
        "bikeRank": 9,
        "bikeTime": "1970-01-01T01:19:07.4600000",
        "T2": "1970-01-01T00:02:27.5140000",
        "runRank": 9,
        "runTime": "1970-01-01T00:52:18.4300000",
        "ageGroupRank": 8,
        "overallRank": 83,
        "total": "1970-01-01T02:34:15.6600000"
    },
    {
        "category": "I",
        "sortOrder": 3,
        "ageGroup": "Male 14 - 16",
        "bibNumber": 401,
        "name": "Andy Pascual",
        "gender": "M",
        "age": 16,
        "swimRank": 8,
        "swimTime": "1970-01-01T00:23:53.6960000",
        "T1": "1970-01-01T00:02:23.6600000",
        "bikeRank": 8,
        "bikeTime": "1970-01-01T01:18:10.2670000",
        "T2": "1970-01-01T00:00:53.1700000",
        "runRank": 10,
        "runTime": "1970-01-01T00:52:22.3070000",
        "ageGroupRank": 9,
        "overallRank": 84,
        "total": "1970-01-01T02:37:43.1000000"
    },
    {
        "category": "I",
        "sortOrder": 3,
        "ageGroup": "Male 14 - 16",
        "bibNumber": 393,
        "name": "David Gonzalez",
        "gender": "M",
        "age": 14,
        "swimRank": 10,
        "swimTime": "1970-01-01T00:25:35.5600000",
        "T1": "1970-01-01T00:03:34.0260000",
        "bikeRank": 10,
        "bikeTime": "1970-01-01T01:28:35.5070000",
        "T2": "1970-01-01T00:00:51.6270000",
        "runRank": 7,
        "runTime": "1970-01-01T00:39:33.5300000",
        "ageGroupRank": 10,
        "overallRank": 85,
        "total": "1970-01-01T02:38:10.2500000"
    },
    {
        "category": "I",
        "sortOrder": 3,
        "ageGroup": "Male 17 - 19",
        "bibNumber": 407,
        "name": "Eric Wilkens",
        "gender": "M",
        "age": 18,
        "swimRank": 1,
        "swimTime": "1970-01-01T00:13:58.1130000",
        "T1": "1970-01-01T00:01:40.4430000",
        "bikeRank": 2,
        "bikeTime": "1970-01-01T00:56:01.0500000",
        "T2": "1970-01-01T00:01:04.9570000",
        "runRank": 1,
        "runTime": "1970-01-01T00:32:08.7730000",
        "ageGroupRank": 1,
        "overallRank": 19,
        "total": "1970-01-01T01:44:53.3360000"
    },
    {
        "category": "I",
        "sortOrder": 3,
        "ageGroup": "Male 17 - 19",
        "bibNumber": 406,
        "name": "Matthew Hamerly",
        "gender": "M",
        "age": 18,
        "swimRank": 6,
        "swimTime": "1970-01-01T00:22:04.3360000",
        "T1": "1970-01-01T00:03:43.2440000",
        "bikeRank": 3,
        "bikeTime": "1970-01-01T01:04:28.7830000",
        "T2": "1970-01-01T00:01:34.7130000",
        "runRank": 3,
        "runTime": "1970-01-01T00:35:21.3940000",
        "ageGroupRank": 2,
        "overallRank": 57,
        "total": "1970-01-01T02:07:12.4700000"
    },
    {
        "category": "I",
        "sortOrder": 3,
        "ageGroup": "Male 17 - 19",
        "bibNumber": 403,
        "name": "Jonathan Aguinaga",
        "gender": "M",
        "age": 17,
        "swimRank": 5,
        "swimTime": "1970-01-01T00:21:25.6130000",
        "T1": "1970-01-01T00:02:31.5270000",
        "bikeRank": 7,
        "bikeTime": "1970-01-01T01:12:24.5100000",
        "T2": "1970-01-01T00:00:33.7960000",
        "runRank": 2,
        "runTime": "1970-01-01T00:34:02.9300000",
        "ageGroupRank": 3,
        "overallRank": 63,
        "total": "1970-01-01T02:10:58.3760000"
    },
    {
        "category": "I",
        "sortOrder": 3,
        "ageGroup": "Male 17 - 19",
        "bibNumber": 404,
        "name": "Noah Gloudeman",
        "gender": "M",
        "age": 18,
        "swimRank": 7,
        "swimTime": "1970-01-01T00:24:01.8760000",
        "T1": "1970-01-01T00:03:13.2540000",
        "bikeRank": 5,
        "bikeTime": "1970-01-01T01:06:35.3130000",
        "T2": "1970-01-01T00:01:24.0500000",
        "runRank": 7,
        "runTime": "1970-01-01T00:45:12.1730000",
        "ageGroupRank": 4,
        "overallRank": 71,
        "total": "1970-01-01T02:20:26.6660000"
    },
    {
        "category": "I",
        "sortOrder": 3,
        "ageGroup": "Male 17 - 19",
        "bibNumber": 409,
        "name": "Joshua Mckeever",
        "gender": "M",
        "age": 19,
        "swimRank": 8,
        "swimTime": "1970-01-01T00:30:42.8500000",
        "T1": "1970-01-01T00:02:45.5830000",
        "bikeRank": 8,
        "bikeTime": "1970-01-01T01:13:58.7070000",
        "T2": "1970-01-01T00:01:14.2930000",
        "runRank": 4,
        "runTime": "1970-01-01T00:40:30.5370000",
        "ageGroupRank": 5,
        "overallRank": 77,
        "total": "1970-01-01T02:29:11.9700000"
    },
    {
        "category": "I",
        "sortOrder": 3,
        "ageGroup": "Male 17 - 19",
        "bibNumber": 410,
        "name": "Matthew Wilson",
        "gender": "M",
        "age": 19,
        "swimRank": 4,
        "swimTime": "1970-01-01T00:21:13.5630000",
        "T1": "1970-01-01T00:12:12.5130000",
        "bikeRank": 4,
        "bikeTime": "1970-01-01T01:05:03.7170000",
        "T2": "1970-01-01T00:10:11.2100000",
        "runRank": 6,
        "runTime": "1970-01-01T00:40:32.6730000",
        "ageGroupRank": 6,
        "overallRank": 78,
        "total": "1970-01-01T02:29:13.6760000"
    },
    {
        "category": "I",
        "sortOrder": 3,
        "ageGroup": "Male 17 - 19",
        "bibNumber": 408,
        "name": "Jonathan Im",
        "gender": "M",
        "age": 19,
        "swimRank": 2,
        "swimTime": "1970-01-01T00:19:09.1500000",
        "T1": "1970-01-01T00:14:16.1960000",
        "bikeRank": 6,
        "bikeTime": "1970-01-01T01:11:10.8800000",
        "T2": "1970-01-01T00:04:05.3670000",
        "runRank": 5,
        "runTime": "1970-01-01T00:40:32.0900000",
        "ageGroupRank": 7,
        "overallRank": 79,
        "total": "1970-01-01T02:29:13.6830000"
    },
    {
        "category": "I",
        "sortOrder": 3,
        "ageGroup": "Male 17 - 19",
        "bibNumber": 405,
        "name": "Kaleb Halversen",
        "gender": "M",
        "age": 18,
        "swimRank": 3,
        "swimTime": "1970-01-01T00:19:25.9430000",
        "T1": "1970-01-01T01:23:43.7500000",
        "bikeRank": 1,
        "bikeTime": "1970-01-01T00:00:00.0000000",
        "T2": "1970-01-01T00:02:24.1500000",
        "runRank": 8,
        "runTime": "1970-01-01T00:48:24.8370000",
        "ageGroupRank": 8,
        "overallRank": 82,
        "total": "1970-01-01T02:33:58.6800000"
    },
    {
        "category": "I",
        "sortOrder": 3,
        "ageGroup": "Male 20 - 24",
        "bibNumber": 233,
        "name": "Jeffrey Brownlow",
        "gender": "M",
        "age": 23,
        "swimRank": 3,
        "swimTime": "1970-01-01T00:12:03.5270000",
        "T1": "1970-01-01T00:02:22.6200000",
        "bikeRank": 3,
        "bikeTime": "1970-01-01T00:53:55.8000000",
        "T2": "1970-01-01T00:01:07.1300000",
        "runRank": 1,
        "runTime": "1970-01-01T00:26:04.4000000",
        "ageGroupRank": 1,
        "overallRank": 11,
        "total": "1970-01-01T01:35:33.4770000"
    },
    {
        "category": "I",
        "sortOrder": 3,
        "ageGroup": "Male 20 - 24",
        "bibNumber": 203,
        "name": "Spencer Pflug",
        "gender": "M",
        "age": 20,
        "swimRank": 1,
        "swimTime": null,
        "T1": null,
        "bikeRank": 2,
        "bikeTime": "1970-01-01T00:53:43.0860000",
        "T2": "1970-01-01T00:01:03.9900000",
        "runRank": 2,
        "runTime": "1970-01-01T00:30:17.0140000",
        "ageGroupRank": 2,
        "overallRank": 18,
        "total": "1970-01-01T01:42:37.1470000"
    },
    {
        "category": "I",
        "sortOrder": 3,
        "ageGroup": "Male 20 - 24",
        "bibNumber": 207,
        "name": "Joshua Yang",
        "gender": "M",
        "age": 21,
        "swimRank": 5,
        "swimTime": "1970-01-01T00:16:10.8770000",
        "T1": "1970-01-01T00:01:35.8430000",
        "bikeRank": 4,
        "bikeTime": "1970-01-01T00:54:42.1630000",
        "T2": "1970-01-01T00:01:07.2500000",
        "runRank": 3,
        "runTime": "1970-01-01T00:31:58.5900000",
        "ageGroupRank": 3,
        "overallRank": 20,
        "total": "1970-01-01T01:45:34.7230000"
    },
    {
        "category": "I",
        "sortOrder": 3,
        "ageGroup": "Male 20 - 24",
        "bibNumber": 208,
        "name": "Prescott Khair",
        "gender": "M",
        "age": 22,
        "swimRank": 4,
        "swimTime": "1970-01-01T00:15:30.5500000",
        "T1": "1970-01-01T00:01:47.3870000",
        "bikeRank": 5,
        "bikeTime": "1970-01-01T00:59:15.7630000",
        "T2": "1970-01-01T00:01:02.8170000",
        "runRank": 10,
        "runTime": "1970-01-01T00:40:03.4300000",
        "ageGroupRank": 4,
        "overallRank": 42,
        "total": "1970-01-01T01:57:39.9470000"
    },
    {
        "category": "I",
        "sortOrder": 3,
        "ageGroup": "Male 20 - 24",
        "bibNumber": 201,
        "name": "Paul Martin",
        "gender": "M",
        "age": 20,
        "swimRank": 7,
        "swimTime": "1970-01-01T00:16:42.2970000",
        "T1": "1970-01-01T00:03:00.1860000",
        "bikeRank": 7,
        "bikeTime": "1970-01-01T01:02:13.4000000",
        "T2": "1970-01-01T00:01:20.6440000",
        "runRank": 6,
        "runTime": "1970-01-01T00:35:57.9960000",
        "ageGroupRank": 5,
        "overallRank": 44,
        "total": "1970-01-01T01:59:14.5230000"
    },
    {
        "category": "I",
        "sortOrder": 3,
        "ageGroup": "Male 20 - 24",
        "bibNumber": 206,
        "name": "Kyusun Lee",
        "gender": "M",
        "age": 21,
        "swimRank": 9,
        "swimTime": "1970-01-01T00:17:58.3800000",
        "T1": "1970-01-01T00:03:07.6200000",
        "bikeRank": 8,
        "bikeTime": "1970-01-01T01:02:31.9270000",
        "T2": "1970-01-01T00:01:08.2000000",
        "runRank": 4,
        "runTime": "1970-01-01T00:34:55.0860000",
        "ageGroupRank": 6,
        "overallRank": 46,
        "total": "1970-01-01T01:59:41.2130000"
    },
    {
        "category": "I",
        "sortOrder": 3,
        "ageGroup": "Male 20 - 24",
        "bibNumber": 202,
        "name": "Caleb Mckinney",
        "gender": "M",
        "age": 20,
        "swimRank": 8,
        "swimTime": "1970-01-01T00:16:47.5370000",
        "T1": "1970-01-01T01:07:11.5730000",
        "bikeRank": 1,
        "bikeTime": null,
        "T2": null,
        "runRank": 5,
        "runTime": "1970-01-01T00:35:22.9230000",
        "ageGroupRank": 7,
        "overallRank": 50,
        "total": "1970-01-01T02:00:59.4530000"
    },
    {
        "category": "I",
        "sortOrder": 3,
        "ageGroup": "Male 20 - 24",
        "bibNumber": 204,
        "name": "Cameron Beem",
        "gender": "M",
        "age": 21,
        "swimRank": 2,
        "swimTime": null,
        "T1": null,
        "bikeRank": 6,
        "bikeTime": "1970-01-01T01:02:09.8960000",
        "T2": "1970-01-01T00:01:10.7770000",
        "runRank": 12,
        "runTime": "1970-01-01T00:44:29.3430000",
        "ageGroupRank": 8,
        "overallRank": 60,
        "total": "1970-01-01T02:07:56.9230000"
    },
    {
        "category": "I",
        "sortOrder": 3,
        "ageGroup": "Male 20 - 24",
        "bibNumber": 211,
        "name": "Tyler Pflug",
        "gender": "M",
        "age": 23,
        "swimRank": 11,
        "swimTime": "1970-01-01T00:24:26.8530000",
        "T1": "1970-01-01T00:02:37.8600000",
        "bikeRank": 9,
        "bikeTime": "1970-01-01T01:02:53.7640000",
        "T2": "1970-01-01T00:01:18.5800000",
        "runRank": 7,
        "runTime": "1970-01-01T00:36:59.1830000",
        "ageGroupRank": 9,
        "overallRank": 61,
        "total": "1970-01-01T02:08:16.2400000"
    },
    {
        "category": "I",
        "sortOrder": 3,
        "ageGroup": "Male 20 - 24",
        "bibNumber": 212,
        "name": "Zachary Myers",
        "gender": "M",
        "age": 24,
        "swimRank": 6,
        "swimTime": "1970-01-01T00:16:14.0530000",
        "T1": "1970-01-01T00:03:54.9670000",
        "bikeRank": 10,
        "bikeTime": "1970-01-01T01:03:27.3770000",
        "T2": "1970-01-01T00:04:24.8760000",
        "runRank": 13,
        "runTime": "1970-01-01T00:47:22.1540000",
        "ageGroupRank": 10,
        "overallRank": 68,
        "total": "1970-01-01T02:15:23.4270000"
    },
    {
        "category": "I",
        "sortOrder": 3,
        "ageGroup": "Male 20 - 24",
        "bibNumber": 210,
        "name": "Josef Myers",
        "gender": "M",
        "age": 23,
        "swimRank": 10,
        "swimTime": "1970-01-01T00:23:26.3170000",
        "T1": "1970-01-01T00:02:46.6330000",
        "bikeRank": 11,
        "bikeTime": "1970-01-01T01:08:36.6500000",
        "T2": "1970-01-01T00:01:26.9100000",
        "runRank": 11,
        "runTime": "1970-01-01T00:42:12.7230000",
        "ageGroupRank": 11,
        "overallRank": 69,
        "total": "1970-01-01T02:18:29.2330000"
    },
    {
        "category": "I",
        "sortOrder": 3,
        "ageGroup": "Male 20 - 24",
        "bibNumber": 205,
        "name": "Daniel Hawkins",
        "gender": "M",
        "age": 21,
        "swimRank": 12,
        "swimTime": "1970-01-01T00:27:02.7730000",
        "T1": "1970-01-01T00:06:27.5940000",
        "bikeRank": 13,
        "bikeTime": "1970-01-01T01:17:55.3400000",
        "T2": "1970-01-01T00:01:26.6130000",
        "runRank": 8,
        "runTime": "1970-01-01T00:38:05.3700000",
        "ageGroupRank": 12,
        "overallRank": 80,
        "total": "1970-01-01T02:30:57.6900000"
    },
    {
        "category": "I",
        "sortOrder": 3,
        "ageGroup": "Male 20 - 24",
        "bibNumber": 209,
        "name": "Jesse Liu",
        "gender": "M",
        "age": 22,
        "swimRank": 13,
        "swimTime": "1970-01-01T00:27:25.0770000",
        "T1": "1970-01-01T00:06:05.0860000",
        "bikeRank": 12,
        "bikeTime": "1970-01-01T01:17:07.4840000",
        "T2": "1970-01-01T00:02:14.8030000",
        "runRank": 9,
        "runTime": "1970-01-01T00:38:05.3700000",
        "ageGroupRank": 13,
        "overallRank": 81,
        "total": "1970-01-01T02:30:57.8200000"
    },
    {
        "category": "I",
        "sortOrder": 3,
        "ageGroup": "Male 25 - 29",
        "bibNumber": 214,
        "name": "Danny Mcbride",
        "gender": "M",
        "age": 26,
        "swimRank": 2,
        "swimTime": "1970-01-01T00:16:01.5200000",
        "T1": "1970-01-01T00:02:22.6730000",
        "bikeRank": 2,
        "bikeTime": "1970-01-01T00:57:26.8070000",
        "T2": "1970-01-01T00:01:21.9870000",
        "runRank": 2,
        "runTime": "1970-01-01T00:32:56.8800000",
        "ageGroupRank": 1,
        "overallRank": 28,
        "total": "1970-01-01T01:50:09.8670000"
    },
    {
        "category": "I",
        "sortOrder": 3,
        "ageGroup": "Male 25 - 29",
        "bibNumber": 215,
        "name": "David Hugel",
        "gender": "M",
        "age": 27,
        "swimRank": 1,
        "swimTime": null,
        "T1": null,
        "bikeRank": 1,
        "bikeTime": "1970-01-01T00:00:00.0000000",
        "T2": "1970-01-01T00:01:15.6500000",
        "runRank": 1,
        "runTime": "1970-01-01T00:30:16.4760000",
        "ageGroupRank": 2,
        "overallRank": 32,
        "total": "1970-01-01T01:51:07.3730000"
    },
    {
        "category": "I",
        "sortOrder": 3,
        "ageGroup": "Male 25 - 29",
        "bibNumber": 217,
        "name": "Kurt Osena",
        "gender": "M",
        "age": 29,
        "swimRank": 4,
        "swimTime": "1970-01-01T00:17:19.6000000",
        "T1": "1970-01-01T00:03:13.7870000",
        "bikeRank": 4,
        "bikeTime": "1970-01-01T00:59:32.4200000",
        "T2": "1970-01-01T00:01:45.6730000",
        "runRank": 3,
        "runTime": "1970-01-01T00:33:54.3570000",
        "ageGroupRank": 3,
        "overallRank": 37,
        "total": "1970-01-01T01:55:45.8370000"
    },
    {
        "category": "I",
        "sortOrder": 3,
        "ageGroup": "Male 25 - 29",
        "bibNumber": 213,
        "name": "Steven Kim",
        "gender": "M",
        "age": 26,
        "swimRank": 3,
        "swimTime": "1970-01-01T00:16:58.2830000",
        "T1": "1970-01-01T00:03:31.3700000",
        "bikeRank": 3,
        "bikeTime": "1970-01-01T00:58:22.5270000",
        "T2": "1970-01-01T00:02:40.9230000",
        "runRank": 4,
        "runTime": "1970-01-01T00:34:42.3540000",
        "ageGroupRank": 4,
        "overallRank": 38,
        "total": "1970-01-01T01:56:15.4570000"
    },
    {
        "category": "I",
        "sortOrder": 3,
        "ageGroup": "Male 25 - 29",
        "bibNumber": 216,
        "name": "Genesis Napod",
        "gender": "M",
        "age": 29,
        "swimRank": 5,
        "swimTime": "1970-01-01T00:34:04.3900000",
        "T1": "1970-01-01T00:03:08.4000000",
        "bikeRank": 5,
        "bikeTime": "1970-01-01T01:04:37.8900000",
        "T2": "1970-01-01T00:00:43.8170000",
        "runRank": 5,
        "runTime": "1970-01-01T00:46:25.1330000",
        "ageGroupRank": 5,
        "overallRank": 76,
        "total": "1970-01-01T02:28:59.6300000"
    },
    {
        "category": "I",
        "sortOrder": 3,
        "ageGroup": "Male 30 - 34",
        "bibNumber": 221,
        "name": "Joshua Woods",
        "gender": "M",
        "age": 31,
        "swimRank": 1,
        "swimTime": "1970-01-01T00:11:33.2830000",
        "T1": "1970-01-01T00:01:28.8140000",
        "bikeRank": 4,
        "bikeTime": "1970-01-01T00:47:29.9360000",
        "T2": "1970-01-01T00:00:41.7100000",
        "runRank": 2,
        "runTime": "1970-01-01T00:26:50.1200000",
        "ageGroupRank": 1,
        "overallRank": 4,
        "total": "1970-01-01T01:28:03.8630000"
    },
    {
        "category": "I",
        "sortOrder": 3,
        "ageGroup": "Male 30 - 34",
        "bibNumber": 231,
        "name": "Jeremy Reichmanner",
        "gender": "M",
        "age": 34,
        "swimRank": 4,
        "swimTime": "1970-01-01T00:14:38.3200000",
        "T1": "1970-01-01T00:01:39.4970000",
        "bikeRank": 2,
        "bikeTime": "1970-01-01T00:45:09.5260000",
        "T2": "1970-01-01T00:00:41.1140000",
        "runRank": 5,
        "runTime": "1970-01-01T00:30:45.8300000",
        "ageGroupRank": 2,
        "overallRank": 7,
        "total": "1970-01-01T01:32:54.2870000"
    },
    {
        "category": "I",
        "sortOrder": 3,
        "ageGroup": "Male 30 - 34",
        "bibNumber": 223,
        "name": "Josue Mendoza",
        "gender": "M",
        "age": 32,
        "swimRank": 2,
        "swimTime": "1970-01-01T00:13:05.0030000",
        "T1": "1970-01-01T00:02:11.4970000",
        "bikeRank": 5,
        "bikeTime": "1970-01-01T00:49:20.5330000",
        "T2": "1970-01-01T00:01:22.3670000",
        "runRank": 3,
        "runTime": "1970-01-01T00:27:33.5100000",
        "ageGroupRank": 3,
        "overallRank": 9,
        "total": "1970-01-01T01:33:32.9100000"
    },
    {
        "category": "I",
        "sortOrder": 3,
        "ageGroup": "Male 30 - 34",
        "bibNumber": 226,
        "name": "James Delong",
        "gender": "M",
        "age": 33,
        "swimRank": 6,
        "swimTime": "1970-01-01T00:16:12.7930000",
        "T1": "1970-01-01T00:01:45.5940000",
        "bikeRank": 3,
        "bikeTime": "1970-01-01T00:46:25.6230000",
        "T2": "1970-01-01T00:01:02.1030000",
        "runRank": 4,
        "runTime": "1970-01-01T00:28:20.6800000",
        "ageGroupRank": 4,
        "overallRank": 10,
        "total": "1970-01-01T01:33:46.7930000"
    },
    {
        "category": "I",
        "sortOrder": 3,
        "ageGroup": "Male 30 - 34",
        "bibNumber": 236,
        "name": "Robert Quigley",
        "gender": "M",
        "age": 33,
        "swimRank": 7,
        "swimTime": "1970-01-01T00:16:24.3530000",
        "T1": "1970-01-01T00:02:58.0370000",
        "bikeRank": 6,
        "bikeTime": "1970-01-01T00:57:13.8530000",
        "T2": "1970-01-01T00:01:26.3470000",
        "runRank": 8,
        "runTime": "1970-01-01T00:34:15.5870000",
        "ageGroupRank": 5,
        "overallRank": 33,
        "total": "1970-01-01T01:52:18.1770000"
    },
    {
        "category": "I",
        "sortOrder": 3,
        "ageGroup": "Male 30 - 34",
        "bibNumber": 225,
        "name": "Austin Cone",
        "gender": "M",
        "age": 33,
        "swimRank": 9,
        "swimTime": "1970-01-01T00:17:13.6630000",
        "T1": "1970-01-01T00:01:52.7140000",
        "bikeRank": 11,
        "bikeTime": "1970-01-01T01:08:12.8760000",
        "T2": "1970-01-01T00:00:42.3940000",
        "runRank": 6,
        "runTime": "1970-01-01T00:31:57.0700000",
        "ageGroupRank": 6,
        "overallRank": 47,
        "total": "1970-01-01T01:59:58.7170000"
    },
    {
        "category": "I",
        "sortOrder": 3,
        "ageGroup": "Male 30 - 34",
        "bibNumber": 218,
        "name": "Andrew Burnett",
        "gender": "M",
        "age": 30,
        "swimRank": 11,
        "swimTime": "1970-01-01T00:18:13.5430000",
        "T1": "1970-01-01T01:14:45.7300000",
        "bikeRank": 1,
        "bikeTime": null,
        "T2": null,
        "runRank": 1,
        "runTime": "1970-01-01T00:25:39.1560000",
        "ageGroupRank": 7,
        "overallRank": 48,
        "total": "1970-01-01T02:00:04.8030000"
    },
    {
        "category": "I",
        "sortOrder": 3,
        "ageGroup": "Male 30 - 34",
        "bibNumber": 220,
        "name": "Ryan Eggers",
        "gender": "M",
        "age": 31,
        "swimRank": 8,
        "swimTime": "1970-01-01T00:17:01.9470000",
        "T1": "1970-01-01T00:03:22.6900000",
        "bikeRank": 10,
        "bikeTime": "1970-01-01T01:04:05.1330000",
        "T2": "1970-01-01T00:01:50.3930000",
        "runRank": 7,
        "runTime": "1970-01-01T00:34:14.6740000",
        "ageGroupRank": 8,
        "overallRank": 49,
        "total": "1970-01-01T02:00:34.8370000"
    },
    {
        "category": "I",
        "sortOrder": 3,
        "ageGroup": "Male 30 - 34",
        "bibNumber": 222,
        "name": "Leslie Bojoh",
        "gender": "M",
        "age": 32,
        "swimRank": 13,
        "swimTime": "1970-01-01T00:22:56.7070000",
        "T1": "1970-01-01T00:02:33.9230000",
        "bikeRank": 7,
        "bikeTime": "1970-01-01T00:59:12.1200000",
        "T2": "1970-01-01T00:01:37.2630000",
        "runRank": 9,
        "runTime": "1970-01-01T00:35:39.1300000",
        "ageGroupRank": 9,
        "overallRank": 52,
        "total": "1970-01-01T02:01:59.1430000"
    },
    {
        "category": "I",
        "sortOrder": 3,
        "ageGroup": "Male 30 - 34",
        "bibNumber": 232,
        "name": "Justin Whited",
        "gender": "M",
        "age": 34,
        "swimRank": 5,
        "swimTime": "1970-01-01T00:15:49.0070000",
        "T1": "1970-01-01T00:04:14.3930000",
        "bikeRank": 8,
        "bikeTime": "1970-01-01T01:00:55.2500000",
        "T2": "1970-01-01T00:02:20.2430000",
        "runRank": 10,
        "runTime": "1970-01-01T00:44:09.6100000",
        "ageGroupRank": 10,
        "overallRank": 59,
        "total": "1970-01-01T02:07:28.5030000"
    },
    {
        "category": "I",
        "sortOrder": 3,
        "ageGroup": "Male 30 - 34",
        "bibNumber": 229,
        "name": "Leonard Moses",
        "gender": "M",
        "age": 33,
        "swimRank": 3,
        "swimTime": "1970-01-01T00:13:48.4900000",
        "T1": "1970-01-01T00:03:12.1430000",
        "bikeRank": 9,
        "bikeTime": "1970-01-01T01:02:14.3940000",
        "T2": "1970-01-01T00:01:09.1100000",
        "runRank": 12,
        "runTime": "1970-01-01T00:51:38.6900000",
        "ageGroupRank": 11,
        "overallRank": 64,
        "total": "1970-01-01T02:12:02.8270000"
    },
    {
        "category": "I",
        "sortOrder": 3,
        "ageGroup": "Male 30 - 34",
        "bibNumber": 227,
        "name": "Andy Kim",
        "gender": "M",
        "age": 33,
        "swimRank": 12,
        "swimTime": "1970-01-01T00:19:59.5470000",
        "T1": "1970-01-01T00:03:12.5060000",
        "bikeRank": 12,
        "bikeTime": "1970-01-01T01:10:42.4640000",
        "T2": "1970-01-01T00:02:33.7300000",
        "runRank": 11,
        "runTime": "1970-01-01T00:45:23.9200000",
        "ageGroupRank": 12,
        "overallRank": 72,
        "total": "1970-01-01T02:21:52.1670000"
    },
    {
        "category": "I",
        "sortOrder": 3,
        "ageGroup": "Male 30 - 34",
        "bibNumber": 219,
        "name": "Miles Heidorn",
        "gender": "M",
        "age": 30,
        "swimRank": 10,
        "swimTime": "1970-01-01T00:18:11.2800000",
        "T1": "1970-01-01T00:04:09.0300000",
        "bikeRank": 13,
        "bikeTime": "1970-01-01T01:19:54.0870000",
        "T2": "1970-01-01T00:02:54.3030000",
        "runRank": 13,
        "runTime": "1970-01-01T00:55:55.6770000",
        "ageGroupRank": 13,
        "overallRank": 87,
        "total": "1970-01-01T02:41:04.3770000"
    },
    {
        "category": "I",
        "sortOrder": 3,
        "ageGroup": "Male 35 - 39",
        "bibNumber": 244,
        "name": "Jonathan Sierra",
        "gender": "M",
        "age": 37,
        "swimRank": 2,
        "swimTime": "1970-01-01T00:13:29.6800000",
        "T1": "1970-01-01T00:01:32.5000000",
        "bikeRank": 1,
        "bikeTime": "1970-01-01T00:50:57.4770000",
        "T2": "1970-01-01T00:00:47.0530000",
        "runRank": 1,
        "runTime": "1970-01-01T00:29:08.4200000",
        "ageGroupRank": 1,
        "overallRank": 12,
        "total": "1970-01-01T01:35:55.1300000"
    },
    {
        "category": "I",
        "sortOrder": 3,
        "ageGroup": "Male 35 - 39",
        "bibNumber": 247,
        "name": "Daks Hamner",
        "gender": "M",
        "age": 39,
        "swimRank": 1,
        "swimTime": "1970-01-01T00:12:44.7270000",
        "T1": "1970-01-01T00:02:04.8830000",
        "bikeRank": 2,
        "bikeTime": "1970-01-01T00:53:46.4870000",
        "T2": "1970-01-01T00:01:00.5660000",
        "runRank": 2,
        "runTime": "1970-01-01T00:29:26.1970000",
        "ageGroupRank": 2,
        "overallRank": 14,
        "total": "1970-01-01T01:39:02.8600000"
    },
    {
        "category": "I",
        "sortOrder": 3,
        "ageGroup": "Male 35 - 39",
        "bibNumber": 242,
        "name": "Jason Shives",
        "gender": "M",
        "age": 35,
        "swimRank": 5,
        "swimTime": "1970-01-01T00:15:38.4570000",
        "T1": "1970-01-01T00:01:45.2200000",
        "bikeRank": 4,
        "bikeTime": "1970-01-01T00:56:03.0230000",
        "T2": "1970-01-01T00:01:06.4570000",
        "runRank": 4,
        "runTime": "1970-01-01T00:34:47.2060000",
        "ageGroupRank": 3,
        "overallRank": 26,
        "total": "1970-01-01T01:49:20.3630000"
    },
    {
        "category": "I",
        "sortOrder": 3,
        "ageGroup": "Male 35 - 39",
        "bibNumber": 243,
        "name": "Brian Wiehn",
        "gender": "M",
        "age": 36,
        "swimRank": 3,
        "swimTime": "1970-01-01T00:14:41.4370000",
        "T1": "1970-01-01T00:02:02.7900000",
        "bikeRank": 6,
        "bikeTime": "1970-01-01T00:58:21.7860000",
        "T2": "1970-01-01T00:00:55.8570000",
        "runRank": 3,
        "runTime": "1970-01-01T00:33:46.4470000",
        "ageGroupRank": 4,
        "overallRank": 27,
        "total": "1970-01-01T01:49:48.3170000"
    },
    {
        "category": "I",
        "sortOrder": 3,
        "ageGroup": "Male 35 - 39",
        "bibNumber": 241,
        "name": "Joe La Com",
        "gender": "M",
        "age": 35,
        "swimRank": 4,
        "swimTime": "1970-01-01T00:15:23.8170000",
        "T1": "1970-01-01T00:02:43.7630000",
        "bikeRank": 5,
        "bikeTime": "1970-01-01T00:58:00.3670000",
        "T2": "1970-01-01T00:01:39.8200000",
        "runRank": 5,
        "runTime": "1970-01-01T00:36:28.5760000",
        "ageGroupRank": 5,
        "overallRank": 36,
        "total": "1970-01-01T01:54:16.3430000"
    },
    {
        "category": "I",
        "sortOrder": 3,
        "ageGroup": "Male 35 - 39",
        "bibNumber": 283,
        "name": "Jonathan Geach",
        "gender": "M",
        "age": 37,
        "swimRank": 6,
        "swimTime": "1970-01-01T00:17:54.4670000",
        "T1": "1970-01-01T00:03:58.5330000",
        "bikeRank": 3,
        "bikeTime": "1970-01-01T00:54:12.9200000",
        "T2": "1970-01-01T00:01:39.9730000",
        "runRank": 6,
        "runTime": "1970-01-01T00:39:03.3570000",
        "ageGroupRank": 6,
        "overallRank": 39,
        "total": "1970-01-01T01:56:49.2500000"
    },
    {
        "category": "I",
        "sortOrder": 3,
        "ageGroup": "Male 40 - 44",
        "bibNumber": 281,
        "name": "Jon Eichert",
        "gender": "M",
        "age": 42,
        "swimRank": 2,
        "swimTime": "1970-01-01T00:13:14.0730000",
        "T1": "1970-01-01T00:01:27.0340000",
        "bikeRank": 1,
        "bikeTime": "1970-01-01T00:48:52.0900000",
        "T2": "1970-01-01T00:00:36.3500000",
        "runRank": 1,
        "runTime": "1970-01-01T00:27:08.1800000",
        "ageGroupRank": 1,
        "overallRank": 6,
        "total": "1970-01-01T01:31:17.7270000"
    },
    {
        "category": "I",
        "sortOrder": 3,
        "ageGroup": "Male 40 - 44",
        "bibNumber": 280,
        "name": "Jeff Horn",
        "gender": "M",
        "age": 43,
        "swimRank": 1,
        "swimTime": "1970-01-01T00:07:49.6730000",
        "T1": "1970-01-01T00:06:45.3740000",
        "bikeRank": 2,
        "bikeTime": "1970-01-01T00:50:10.6730000",
        "T2": "1970-01-01T00:01:21.2630000",
        "runRank": 2,
        "runTime": "1970-01-01T00:33:09.0670000",
        "ageGroupRank": 2,
        "overallRank": 17,
        "total": "1970-01-01T01:39:16.0500000"
    },
    {
        "category": "I",
        "sortOrder": 3,
        "ageGroup": "Male 40 - 44",
        "bibNumber": 248,
        "name": "Jimmy Rhodes",
        "gender": "M",
        "age": 40,
        "swimRank": 3,
        "swimTime": "1970-01-01T00:15:52.8170000",
        "T1": "1970-01-01T00:03:36.9000000",
        "bikeRank": 3,
        "bikeTime": "1970-01-01T00:57:23.2660000",
        "T2": "1970-01-01T00:01:53.3840000",
        "runRank": 4,
        "runTime": "1970-01-01T00:38:09.9660000",
        "ageGroupRank": 3,
        "overallRank": 40,
        "total": "1970-01-01T01:56:56.3330000"
    },
    {
        "category": "I",
        "sortOrder": 3,
        "ageGroup": "Male 40 - 44",
        "bibNumber": 251,
        "name": "Shervin Oskouei",
        "gender": "M",
        "age": 44,
        "swimRank": 4,
        "swimTime": "1970-01-01T00:19:07.9070000",
        "T1": "1970-01-01T00:03:46.5300000",
        "bikeRank": 4,
        "bikeTime": "1970-01-01T01:10:27.1630000",
        "T2": "1970-01-01T00:01:49.1530000",
        "runRank": 3,
        "runTime": "1970-01-01T00:38:07.3740000",
        "ageGroupRank": 4,
        "overallRank": 67,
        "total": "1970-01-01T02:13:18.1270000"
    },
    {
        "category": "I",
        "sortOrder": 3,
        "ageGroup": "Male 45 - 49",
        "bibNumber": 257,
        "name": "Bill Tracy",
        "gender": "M",
        "age": 46,
        "swimRank": 1,
        "swimTime": "1970-01-01T00:14:23.0170000",
        "T1": "1970-01-01T00:02:45.6460000",
        "bikeRank": 2,
        "bikeTime": "1970-01-01T00:57:20.7600000",
        "T2": "1970-01-01T00:01:56.1740000",
        "runRank": 4,
        "runTime": "1970-01-01T00:37:10.4760000",
        "ageGroupRank": 1,
        "overallRank": 34,
        "total": "1970-01-01T01:53:36.0730000"
    },
    {
        "category": "I",
        "sortOrder": 3,
        "ageGroup": "Male 45 - 49",
        "bibNumber": 258,
        "name": "Donald Drexler",
        "gender": "M",
        "age": 47,
        "swimRank": 5,
        "swimTime": "1970-01-01T00:18:53.9970000",
        "T1": "1970-01-01T00:02:30.0130000",
        "bikeRank": 1,
        "bikeTime": "1970-01-01T00:56:20.2530000",
        "T2": "1970-01-01T00:01:07.4670000",
        "runRank": 2,
        "runTime": "1970-01-01T00:35:17.6100000",
        "ageGroupRank": 2,
        "overallRank": 35,
        "total": "1970-01-01T01:54:09.3400000"
    },
    {
        "category": "I",
        "sortOrder": 3,
        "ageGroup": "Male 45 - 49",
        "bibNumber": 259,
        "name": "Paul Urbanowicz",
        "gender": "M",
        "age": 49,
        "swimRank": 3,
        "swimTime": "1970-01-01T00:17:38.5570000",
        "T1": "1970-01-01T00:04:22.1330000",
        "bikeRank": 4,
        "bikeTime": "1970-01-01T01:00:58.0430000",
        "T2": "1970-01-01T00:02:04.3440000",
        "runRank": 1,
        "runTime": "1970-01-01T00:32:32.1400000",
        "ageGroupRank": 3,
        "overallRank": 41,
        "total": "1970-01-01T01:57:35.2170000"
    },
    {
        "category": "I",
        "sortOrder": 3,
        "ageGroup": "Male 45 - 49",
        "bibNumber": 253,
        "name": "Sean Otoole",
        "gender": "M",
        "age": 45,
        "swimRank": 2,
        "swimTime": "1970-01-01T00:14:29.3670000",
        "T1": "1970-01-01T00:03:20.9160000",
        "bikeRank": 3,
        "bikeTime": "1970-01-01T01:00:55.7270000",
        "T2": "1970-01-01T00:02:47.3100000",
        "runRank": 3,
        "runTime": "1970-01-01T00:37:05.0670000",
        "ageGroupRank": 4,
        "overallRank": 43,
        "total": "1970-01-01T01:58:38.3870000"
    },
    {
        "category": "I",
        "sortOrder": 3,
        "ageGroup": "Male 45 - 49",
        "bibNumber": 254,
        "name": "Scott Kelley",
        "gender": "M",
        "age": 46,
        "swimRank": 4,
        "swimTime": "1970-01-01T00:18:03.7700000",
        "T1": "1970-01-01T00:02:14.4600000",
        "bikeRank": 5,
        "bikeTime": "1970-01-01T01:01:27.6470000",
        "T2": "1970-01-01T00:02:05.5900000",
        "runRank": 6,
        "runTime": "1970-01-01T00:39:41.9200000",
        "ageGroupRank": 5,
        "overallRank": 54,
        "total": "1970-01-01T02:03:33.3870000"
    },
    {
        "category": "I",
        "sortOrder": 3,
        "ageGroup": "Male 45 - 49",
        "bibNumber": 252,
        "name": "Mark Lickey",
        "gender": "M",
        "age": 45,
        "swimRank": 6,
        "swimTime": "1970-01-01T00:20:33.5170000",
        "T1": "1970-01-01T00:05:42.9760000",
        "bikeRank": 8,
        "bikeTime": "1970-01-01T01:05:19.6770000",
        "T2": "1970-01-01T00:02:01.9670000",
        "runRank": 5,
        "runTime": "1970-01-01T00:38:45.8100000",
        "ageGroupRank": 6,
        "overallRank": 65,
        "total": "1970-01-01T02:12:23.9470000"
    },
    {
        "category": "I",
        "sortOrder": 3,
        "ageGroup": "Male 45 - 49",
        "bibNumber": 279,
        "name": "Matthew Davis",
        "gender": "M",
        "age": 48,
        "swimRank": 7,
        "swimTime": "1970-01-01T00:23:44.2030000",
        "T1": "1970-01-01T00:03:50.6270000",
        "bikeRank": 6,
        "bikeTime": "1970-01-01T01:02:58.1370000",
        "T2": "1970-01-01T00:01:43.4460000",
        "runRank": 7,
        "runTime": "1970-01-01T00:40:17.3640000",
        "ageGroupRank": 7,
        "overallRank": 66,
        "total": "1970-01-01T02:12:33.7770000"
    },
    {
        "category": "I",
        "sortOrder": 3,
        "ageGroup": "Male 45 - 49",
        "bibNumber": 255,
        "name": "Kevin Martin",
        "gender": "M",
        "age": 46,
        "swimRank": 8,
        "swimTime": "1970-01-01T00:33:16.5670000",
        "T1": "1970-01-01T00:05:29.6900000",
        "bikeRank": 7,
        "bikeTime": "1970-01-01T01:04:49.8360000",
        "T2": "1970-01-01T00:04:44.0740000",
        "runRank": 8,
        "runTime": "1970-01-01T00:51:28.0330000",
        "ageGroupRank": 8,
        "overallRank": 86,
        "total": "1970-01-01T02:39:48.2000000"
    },
    {
        "category": "I",
        "sortOrder": 3,
        "ageGroup": "Male 50 - 54",
        "bibNumber": 264,
        "name": "Carlton Vollberg",
        "gender": "M",
        "age": 50,
        "swimRank": 2,
        "swimTime": null,
        "T1": null,
        "bikeRank": 1,
        "bikeTime": "1970-01-01T00:47:48.6500000",
        "T2": "1970-01-01T00:01:04.8530000",
        "runRank": 1,
        "runTime": "1970-01-01T00:28:51.6070000",
        "ageGroupRank": 1,
        "overallRank": 8,
        "total": "1970-01-01T01:32:59.3000000"
    },
    {
        "category": "I",
        "sortOrder": 3,
        "ageGroup": "Male 50 - 54",
        "bibNumber": 266,
        "name": "Ed Rusk",
        "gender": "M",
        "age": 51,
        "swimRank": 6,
        "swimTime": "1970-01-01T00:14:40.0070000",
        "T1": "1970-01-01T00:02:07.5130000",
        "bikeRank": 2,
        "bikeTime": "1970-01-01T00:49:55.6700000",
        "T2": "1970-01-01T00:00:46.2200000",
        "runRank": 2,
        "runTime": "1970-01-01T00:29:35.1200000",
        "ageGroupRank": 2,
        "overallRank": 13,
        "total": "1970-01-01T01:37:04.5300000"
    },
    {
        "category": "I",
        "sortOrder": 3,
        "ageGroup": "Male 50 - 54",
        "bibNumber": 268,
        "name": "Timothy Wolf",
        "gender": "M",
        "age": 51,
        "swimRank": 3,
        "swimTime": "1970-01-01T00:10:22.7470000",
        "T1": "1970-01-01T00:02:20.4230000",
        "bikeRank": 3,
        "bikeTime": "1970-01-01T00:55:17.0070000",
        "T2": "1970-01-01T00:01:17.5830000",
        "runRank": 3,
        "runTime": "1970-01-01T00:29:49.2900000",
        "ageGroupRank": 3,
        "overallRank": 15,
        "total": "1970-01-01T01:39:07.0500000"
    },
    {
        "category": "I",
        "sortOrder": 3,
        "ageGroup": "Male 50 - 54",
        "bibNumber": 262,
        "name": "Craig Kirksey",
        "gender": "M",
        "age": 50,
        "swimRank": 4,
        "swimTime": "1970-01-01T00:12:23.8070000",
        "T1": "1970-01-01T00:02:53.4100000",
        "bikeRank": 6,
        "bikeTime": "1970-01-01T00:57:15.2430000",
        "T2": "1970-01-01T00:01:40.2630000",
        "runRank": 5,
        "runTime": "1970-01-01T00:33:03.7670000",
        "ageGroupRank": 4,
        "overallRank": 23,
        "total": "1970-01-01T01:47:16.4900000"
    },
    {
        "category": "I",
        "sortOrder": 3,
        "ageGroup": "Male 50 - 54",
        "bibNumber": 263,
        "name": "Martin Klingbeil",
        "gender": "M",
        "age": 50,
        "swimRank": 8,
        "swimTime": "1970-01-01T00:18:18.9470000",
        "T1": "1970-01-01T00:01:58.2700000",
        "bikeRank": 5,
        "bikeTime": "1970-01-01T00:56:55.2630000",
        "T2": "1970-01-01T00:01:21.3730000",
        "runRank": 4,
        "runTime": "1970-01-01T00:31:39.5870000",
        "ageGroupRank": 5,
        "overallRank": 29,
        "total": "1970-01-01T01:50:13.4400000"
    },
    {
        "category": "I",
        "sortOrder": 3,
        "ageGroup": "Male 50 - 54",
        "bibNumber": 267,
        "name": "Ivey Williamson",
        "gender": "M",
        "age": 51,
        "swimRank": 5,
        "swimTime": "1970-01-01T00:12:37.8000000",
        "T1": "1970-01-01T00:01:36.2430000",
        "bikeRank": 4,
        "bikeTime": "1970-01-01T00:55:44.6500000",
        "T2": "1970-01-01T00:01:14.1400000",
        "runRank": 9,
        "runTime": "1970-01-01T00:39:19.9170000",
        "ageGroupRank": 6,
        "overallRank": 30,
        "total": "1970-01-01T01:50:32.7500000"
    },
    {
        "category": "I",
        "sortOrder": 3,
        "ageGroup": "Male 50 - 54",
        "bibNumber": 282,
        "name": "John Brownlow",
        "gender": "M",
        "age": 53,
        "swimRank": 7,
        "swimTime": "1970-01-01T00:15:10.8200000",
        "T1": "1970-01-01T00:03:14.8970000",
        "bikeRank": 7,
        "bikeTime": "1970-01-01T00:57:58.0200000",
        "T2": "1970-01-01T00:01:57.3200000",
        "runRank": 10,
        "runTime": "1970-01-01T00:41:07.5360000",
        "ageGroupRank": 7,
        "overallRank": 45,
        "total": "1970-01-01T01:59:28.5930000"
    },
    {
        "category": "I",
        "sortOrder": 3,
        "ageGroup": "Male 50 - 54",
        "bibNumber": 265,
        "name": "Shawn Engle",
        "gender": "M",
        "age": 51,
        "swimRank": 11,
        "swimTime": "1970-01-01T00:21:15.6730000",
        "T1": "1970-01-01T00:03:43.3640000",
        "bikeRank": 8,
        "bikeTime": "1970-01-01T01:00:11.5360000",
        "T2": "1970-01-01T00:01:44.1300000",
        "runRank": 6,
        "runTime": "1970-01-01T00:36:04.5040000",
        "ageGroupRank": 8,
        "overallRank": 53,
        "total": "1970-01-01T02:02:59.2070000"
    },
    {
        "category": "I",
        "sortOrder": 3,
        "ageGroup": "Male 50 - 54",
        "bibNumber": 269,
        "name": "Brad Carrick",
        "gender": "M",
        "age": 53,
        "swimRank": 10,
        "swimTime": "1970-01-01T00:20:29.0870000",
        "T1": "1970-01-01T00:03:22.7260000",
        "bikeRank": 9,
        "bikeTime": "1970-01-01T01:01:33.1870000",
        "T2": "1970-01-01T00:01:44.0070000",
        "runRank": 8,
        "runTime": "1970-01-01T00:39:19.1830000",
        "ageGroupRank": 9,
        "overallRank": 55,
        "total": "1970-01-01T02:06:28.1900000"
    },
    {
        "category": "I",
        "sortOrder": 3,
        "ageGroup": "Male 50 - 54",
        "bibNumber": 261,
        "name": "Todd Hunt",
        "gender": "M",
        "age": 50,
        "swimRank": 1,
        "swimTime": null,
        "T1": null,
        "bikeRank": 11,
        "bikeTime": "1970-01-01T01:12:36.5760000",
        "T2": "1970-01-01T00:01:42.7570000",
        "runRank": 7,
        "runTime": "1970-01-01T00:36:47.8470000",
        "ageGroupRank": 10,
        "overallRank": 56,
        "total": "1970-01-01T02:07:09.5470000"
    },
    {
        "category": "I",
        "sortOrder": 3,
        "ageGroup": "Male 50 - 54",
        "bibNumber": 278,
        "name": "Steve Tompkins",
        "gender": "M",
        "age": 54,
        "swimRank": 9,
        "swimTime": "1970-01-01T00:19:43.3570000",
        "T1": "1970-01-01T00:02:34.5430000",
        "bikeRank": 10,
        "bikeTime": "1970-01-01T01:02:02.1270000",
        "T2": "1970-01-01T00:01:54.0430000",
        "runRank": 11,
        "runTime": "1970-01-01T00:42:57.0000000",
        "ageGroupRank": 11,
        "overallRank": 62,
        "total": "1970-01-01T02:09:11.0700000"
    },
    {
        "category": "I",
        "sortOrder": 3,
        "ageGroup": "Male 55 - 59",
        "bibNumber": 272,
        "name": "Rick Peters",
        "gender": "M",
        "age": 56,
        "swimRank": 1,
        "swimTime": "1970-01-01T00:15:02.1070000",
        "T1": "1970-01-01T00:02:42.4500000",
        "bikeRank": 1,
        "bikeTime": "1970-01-01T00:58:54.8130000",
        "T2": "1970-01-01T00:01:20.8270000",
        "runRank": 1,
        "runTime": "1970-01-01T00:32:58.8130000",
        "ageGroupRank": 1,
        "overallRank": 31,
        "total": "1970-01-01T01:50:59.0100000"
    },
    {
        "category": "I",
        "sortOrder": 3,
        "ageGroup": "Male 60 and Over",
        "bibNumber": 275,
        "name": "Roger Mills",
        "gender": "M",
        "age": 70,
        "swimRank": 2,
        "swimTime": "1970-01-01T00:25:27.4770000",
        "T1": "1970-01-01T00:01:30.1260000",
        "bikeRank": 3,
        "bikeTime": "1970-01-01T01:04:10.6340000",
        "T2": null,
        "runRank": 1,
        "runTime": null,
        "ageGroupRank": 1,
        "overallRank": 70,
        "total": "1970-01-01T02:19:04.9770000"
    },
    {
        "category": "I",
        "sortOrder": 3,
        "ageGroup": "Male 60 and Over",
        "bibNumber": 274,
        "name": "Ralston Maloney",
        "gender": "M",
        "age": 67,
        "swimRank": 3,
        "swimTime": "1970-01-01T00:28:40.8370000",
        "T1": "1970-01-01T00:02:57.8960000",
        "bikeRank": 2,
        "bikeTime": "1970-01-01T00:59:21.7300000",
        "T2": "1970-01-01T00:04:01.8640000",
        "runRank": 3,
        "runTime": "1970-01-01T00:49:00.9600000",
        "ageGroupRank": 2,
        "overallRank": 73,
        "total": "1970-01-01T02:24:03.2870000"
    },
    {
        "category": "I",
        "sortOrder": 3,
        "ageGroup": "Male 60 and Over",
        "bibNumber": 390,
        "name": "Brian Adams",
        "gender": "M",
        "age": 99,
        "swimRank": 1,
        "swimTime": null,
        "T1": null,
        "bikeRank": 1,
        "bikeTime": null,
        "T2": null,
        "runRank": 2,
        "runTime": null,
        "ageGroupRank": 3,
        "overallRank": 74,
        "total": "1970-01-01T02:26:05.6130000"
    },
    {
        "category": "I",
        "sortOrder": 2,
        "ageGroup": "Male Master",
        "bibNumber": 260,
        "name": "Todd Wilkens",
        "gender": "M",
        "age": 49,
        "swimRank": 1,
        "swimTime": "1970-01-01T00:12:52.5400000",
        "T1": "1970-01-01T00:01:32.6170000",
        "bikeRank": 1,
        "bikeTime": "1970-01-01T00:47:48.3630000",
        "T2": "1970-01-01T00:00:36.9670000",
        "runRank": 1,
        "runTime": "1970-01-01T00:28:06.4800000",
        "ageGroupRank": 1,
        "overallRank": 5,
        "total": "1970-01-01T01:30:56.9670000"
    },
    {
        "category": "I",
        "sortOrder": 1,
        "ageGroup": "Male Overall",
        "bibNumber": 234,
        "name": "Seth Ruhling",
        "gender": "M",
        "age": 22,
        "swimRank": 1,
        "swimTime": null,
        "T1": null,
        "bikeRank": 1,
        "bikeTime": null,
        "T2": null,
        "runRank": 1,
        "runTime": "1970-01-01T00:22:35.4600000",
        "ageGroupRank": 1,
        "overallRank": 1,
        "total": "1970-01-01T01:22:07.9570000"
    },
    {
        "category": "I",
        "sortOrder": 1,
        "ageGroup": "Male Overall",
        "bibNumber": 224,
        "name": "George News",
        "gender": "M",
        "age": 32,
        "swimRank": 2,
        "swimTime": "1970-01-01T00:10:43.7700000",
        "T1": "1970-01-01T00:01:11.0400000",
        "bikeRank": 2,
        "bikeTime": "1970-01-01T00:45:28.3570000",
        "T2": "1970-01-01T00:00:40.2400000",
        "runRank": 3,
        "runTime": "1970-01-01T00:25:35.4600000",
        "ageGroupRank": 2,
        "overallRank": 2,
        "total": "1970-01-01T01:23:38.8670000"
    },
    {
        "category": "I",
        "sortOrder": 1,
        "ageGroup": "Male Overall",
        "bibNumber": 235,
        "name": "John Wiygul",
        "gender": "M",
        "age": 27,
        "swimRank": 3,
        "swimTime": "1970-01-01T00:10:52.6730000",
        "T1": "1970-01-01T00:01:11.5670000",
        "bikeRank": 3,
        "bikeTime": "1970-01-01T00:46:13.4600000",
        "T2": "1970-01-01T00:00:41.0200000",
        "runRank": 2,
        "runTime": "1970-01-01T00:24:57.0030000",
        "ageGroupRank": 3,
        "overallRank": 3,
        "total": "1970-01-01T01:23:55.7230000"
    },
    {
        "category": "R",
        "sortOrder": 3,
        "ageGroup": "Male Relay",
        "bibNumber": 287,
        "name": "The Pecan Tarts",
        "gender": "M",
        "age": 38,
        "swimRank": 3,
        "swimTime": "1970-01-01T00:16:35.6770000",
        "T1": "1970-01-01T00:01:16.8130000",
        "bikeRank": 1,
        "bikeTime": "1970-01-01T00:55:11.0170000",
        "T2": "1970-01-01T00:00:42.4860000",
        "runRank": 4,
        "runTime": "1970-01-01T00:32:45.0170000",
        "ageGroupRank": 1,
        "overallRank": 1,
        "total": "1970-01-01T01:46:31.0100000"
    },
    {
        "category": "R",
        "sortOrder": 3,
        "ageGroup": "Male Relay",
        "bibNumber": 291,
        "name": "JUST4FUN",
        "gender": "M",
        "age": 41,
        "swimRank": 2,
        "swimTime": "1970-01-01T00:14:45.8400000",
        "T1": "1970-01-01T00:01:21.6900000",
        "bikeRank": 2,
        "bikeTime": "1970-01-01T00:59:12.0700000",
        "T2": "1970-01-01T00:00:33.8900000",
        "runRank": 5,
        "runTime": "1970-01-01T00:32:52.3230000",
        "ageGroupRank": 2,
        "overallRank": 2,
        "total": "1970-01-01T01:48:45.8130000"
    },
    {
        "category": "R",
        "sortOrder": 3,
        "ageGroup": "Male Relay",
        "bibNumber": 293,
        "name": "Hunky",
        "gender": "M",
        "age": 20,
        "swimRank": 1,
        "swimTime": "1970-01-01T00:14:30.3230000",
        "T1": "1970-01-01T00:01:16.5740000",
        "bikeRank": 4,
        "bikeTime": "1970-01-01T01:06:37.0600000",
        "T2": "1970-01-01T00:00:29.0460000",
        "runRank": 2,
        "runTime": "1970-01-01T00:30:20.2640000",
        "ageGroupRank": 3,
        "overallRank": 3,
        "total": "1970-01-01T01:53:13.2670000"
    },
    {
        "category": "R",
        "sortOrder": 3,
        "ageGroup": "Male Relay",
        "bibNumber": 298,
        "name": "Snap  Crackle &amp; Pop",
        "gender": "M",
        "age": 13,
        "swimRank": 4,
        "swimTime": "1970-01-01T00:17:12.6400000",
        "T1": "1970-01-01T00:01:25.8730000",
        "bikeRank": 5,
        "bikeTime": "1970-01-01T01:06:53.2940000",
        "T2": "1970-01-01T00:00:55.8560000",
        "runRank": 1,
        "runTime": "1970-01-01T00:29:40.2640000",
        "ageGroupRank": 4,
        "overallRank": 4,
        "total": "1970-01-01T01:56:07.9270000"
    },
    {
        "category": "R",
        "sortOrder": 3,
        "ageGroup": "Male Relay",
        "bibNumber": 288,
        "name": "BFJ",
        "gender": "M",
        "age": 46,
        "swimRank": 5,
        "swimTime": "1970-01-01T00:20:56.9370000",
        "T1": "1970-01-01T00:01:32.6300000",
        "bikeRank": 3,
        "bikeTime": "1970-01-01T01:05:05.7560000",
        "T2": "1970-01-01T00:00:46.8940000",
        "runRank": 6,
        "runTime": "1970-01-01T00:35:00.3830000",
        "ageGroupRank": 5,
        "overallRank": 5,
        "total": "1970-01-01T02:03:22.6000000"
    },
    {
        "category": "R",
        "sortOrder": 3,
        "ageGroup": "Male Relay",
        "bibNumber": 299,
        "name": "Splash  Flash &amp; Dash",
        "gender": "M",
        "age": 11,
        "swimRank": 6,
        "swimTime": "1970-01-01T00:21:44.1670000",
        "T1": "1970-01-01T00:01:17.3330000",
        "bikeRank": 6,
        "bikeTime": "1970-01-01T01:14:56.8970000",
        "T2": "1970-01-01T00:00:36.0560000",
        "runRank": 3,
        "runTime": "1970-01-01T00:32:02.3270000",
        "ageGroupRank": 6,
        "overallRank": 6,
        "total": "1970-01-01T02:10:36.7800000"
    },
    {
        "category": "R",
        "sortOrder": 3,
        "ageGroup": "Mixed Relay",
        "bibNumber": 292,
        "name": "The Hermanators",
        "gender": "M",
        "age": 32,
        "swimRank": 6,
        "swimTime": "1970-01-01T00:16:16.7330000",
        "T1": "1970-01-01T00:02:10.5070000",
        "bikeRank": 4,
        "bikeTime": "1970-01-01T00:56:44.0800000",
        "T2": "1970-01-01T00:00:36.6700000",
        "runRank": 1,
        "runTime": "1970-01-01T00:30:21.0130000",
        "ageGroupRank": 1,
        "overallRank": 1,
        "total": "1970-01-01T01:46:09.0030000"
    },
    {
        "category": "R",
        "sortOrder": 3,
        "ageGroup": "Mixed Relay",
        "bibNumber": 412,
        "name": "Brownlow",
        "gender": "M",
        "age": 54,
        "swimRank": 3,
        "swimTime": "1970-01-01T00:12:42.2770000",
        "T1": "1970-01-01T00:02:28.5330000",
        "bikeRank": 2,
        "bikeTime": "1970-01-01T00:54:02.5470000",
        "T2": "1970-01-01T00:00:48.6160000",
        "runRank": 8,
        "runTime": "1970-01-01T00:37:37.4770000",
        "ageGroupRank": 2,
        "overallRank": 2,
        "total": "1970-01-01T01:47:39.4500000"
    },
    {
        "category": "R",
        "sortOrder": 3,
        "ageGroup": "Mixed Relay",
        "bibNumber": 304,
        "name": "We`re Relay-ted",
        "gender": "M",
        "age": 34,
        "swimRank": 4,
        "swimTime": "1970-01-01T00:13:34.8000000",
        "T1": "1970-01-01T00:01:13.3800000",
        "bikeRank": 3,
        "bikeTime": "1970-01-01T00:56:30.6400000",
        "T2": "1970-01-01T00:01:31.5830000",
        "runRank": 5,
        "runTime": "1970-01-01T00:35:27.0240000",
        "ageGroupRank": 3,
        "overallRank": 3,
        "total": "1970-01-01T01:48:17.4270000"
    },
    {
        "category": "R",
        "sortOrder": 3,
        "ageGroup": "Mixed Relay",
        "bibNumber": 364,
        "name": "Krohne",
        "gender": "M",
        "age": 27,
        "swimRank": 2,
        "swimTime": null,
        "T1": null,
        "bikeRank": 5,
        "bikeTime": "1970-01-01T00:59:23.4660000",
        "T2": "1970-01-01T00:02:29.1940000",
        "runRank": 4,
        "runTime": "1970-01-01T00:34:33.0930000",
        "ageGroupRank": 4,
        "overallRank": 4,
        "total": "1970-01-01T01:52:33.4400000"
    },
    {
        "category": "R",
        "sortOrder": 3,
        "ageGroup": "Mixed Relay",
        "bibNumber": 295,
        "name": "Lady and the Champs",
        "gender": "M",
        "age": 59,
        "swimRank": 5,
        "swimTime": "1970-01-01T00:14:39.0570000",
        "T1": "1970-01-01T00:04:37.9430000",
        "bikeRank": 8,
        "bikeTime": "1970-01-01T01:07:03.3570000",
        "T2": "1970-01-01T00:00:46.8300000",
        "runRank": 2,
        "runTime": "1970-01-01T00:30:54.7760000",
        "ageGroupRank": 5,
        "overallRank": 5,
        "total": "1970-01-01T01:58:01.9630000"
    },
    {
        "category": "R",
        "sortOrder": 3,
        "ageGroup": "Mixed Relay",
        "bibNumber": 289,
        "name": "Erskine One",
        "gender": "M",
        "age": 44,
        "swimRank": 8,
        "swimTime": "1970-01-01T00:19:38.0370000",
        "T1": "1970-01-01T00:01:33.7430000",
        "bikeRank": 6,
        "bikeTime": "1970-01-01T01:05:17.0770000",
        "T2": "1970-01-01T00:00:36.6200000",
        "runRank": 7,
        "runTime": "1970-01-01T00:36:06.4330000",
        "ageGroupRank": 6,
        "overallRank": 6,
        "total": "1970-01-01T02:03:11.9100000"
    },
    {
        "category": "R",
        "sortOrder": 3,
        "ageGroup": "Mixed Relay",
        "bibNumber": 290,
        "name": "Erskine Two",
        "gender": "M",
        "age": 40,
        "swimRank": 9,
        "swimTime": "1970-01-01T00:19:38.6870000",
        "T1": "1970-01-01T01:09:02.7500000",
        "bikeRank": 1,
        "bikeTime": "1970-01-01T00:00:00.0000000",
        "T2": "1970-01-01T00:00:38.3960000",
        "runRank": 6,
        "runTime": "1970-01-01T00:35:28.2870000",
        "ageGroupRank": 7,
        "overallRank": 7,
        "total": "1970-01-01T02:04:48.1200000"
    },
    {
        "category": "R",
        "sortOrder": 3,
        "ageGroup": "Mixed Relay",
        "bibNumber": 307,
        "name": "PeTyAl",
        "gender": "M",
        "age": 16,
        "swimRank": 11,
        "swimTime": "1970-01-01T00:21:49.9700000",
        "T1": "1970-01-01T00:01:16.1370000",
        "bikeRank": 7,
        "bikeTime": "1970-01-01T01:05:53.3330000",
        "T2": "1970-01-01T00:00:46.4000000",
        "runRank": 11,
        "runTime": "1970-01-01T00:47:59.4130000",
        "ageGroupRank": 8,
        "overallRank": 8,
        "total": "1970-01-01T02:17:45.2530000"
    },
    {
        "category": "R",
        "sortOrder": 3,
        "ageGroup": "Mixed Relay",
        "bibNumber": 302,
        "name": "KyRoAsh",
        "gender": "M",
        "age": 16,
        "swimRank": 10,
        "swimTime": "1970-01-01T00:20:34.7200000",
        "T1": "1970-01-01T00:01:30.4570000",
        "bikeRank": 10,
        "bikeTime": "1970-01-01T01:24:24.9660000",
        "T2": "1970-01-01T00:00:45.8240000",
        "runRank": 9,
        "runTime": "1970-01-01T00:38:19.9860000",
        "ageGroupRank": 9,
        "overallRank": 9,
        "total": "1970-01-01T02:25:35.9530000"
    },
    {
        "category": "R",
        "sortOrder": 3,
        "ageGroup": "Mixed Relay",
        "bibNumber": 303,
        "name": "JaEmYo",
        "gender": "M",
        "age": 15,
        "swimRank": 1,
        "swimTime": null,
        "T1": null,
        "bikeRank": 9,
        "bikeTime": "1970-01-01T01:22:41.8640000",
        "T2": "1970-01-01T00:00:59.3800000",
        "runRank": 10,
        "runTime": "1970-01-01T00:42:26.3230000",
        "ageGroupRank": 10,
        "overallRank": 10,
        "total": "1970-01-01T02:25:37.1200000"
    },
    {
        "category": "R",
        "sortOrder": 3,
        "ageGroup": "Mixed Relay",
        "bibNumber": 305,
        "name": "SteLaJa",
        "gender": "M",
        "age": 15,
        "swimRank": 7,
        "swimTime": "1970-01-01T00:18:32.5170000",
        "T1": "1970-01-01T00:01:16.4130000",
        "bikeRank": 11,
        "bikeTime": "1970-01-01T01:39:45.6000000",
        "T2": "1970-01-01T00:00:32.4030000",
        "runRank": 3,
        "runTime": "1970-01-01T00:33:54.4270000",
        "ageGroupRank": 11,
        "overallRank": 11,
        "total": "1970-01-01T02:34:01.3600000"
    }
]